Workbook

Sheet README
A1: PriorityOne: source data
A2: One tab per source system, holding the exact rows the demo app was seeded with, shaped the way each system would deliver them.
A3: All accounts, people, figures and links are invented mock data.
A4: Data as of the week of 05 Oct 2026. Regenerate after seeding: python export_sources.py
A5: Blue text = an input you can change. Green text = a formula pulling from another tab. Hover a tab's A1 cell for notes.
A7: Tab | B7: Source System | C7: What It Holds | D7: Feeds These Signals | E7: Rows
A8: SF Accounts | B8: Salesforce | C8: Accounts: segment, ARR, owner, contacts, exec activity | D8: contact_departed, exec_sponsor_gap, single_threaded; importance | E8: =COUNTA('SF Accounts'!A:A)-1
A9: SF Contacts | B9: Salesforce | C9: People at each customer: role, email, last activity | D9: contact ranking, email drafts, suggested steps | E9: =COUNTA('SF Contacts'!A:A)-1
A10: SF Contracts | B10: Salesforce | C10: Contracts and their end (renewal) dates | D10: renewal_approaching | E10: =COUNTA('SF Contracts'!A:A)-1
A11: SF QBR Events | B11: Salesforce | C11: Latest QBR per account | D11: qbr_overdue, no_contact_90d | E11: =COUNTA('SF QBR Events'!A:A)-1
A12: Payments weekly | B12: Payments data warehouse | C12: Weekly volume, auth rate, chargebacks, failed payouts | D12: volume_drop, volume_growth, auth_rate_drop, chargeback_spike, failed_payout | E12: =COUNTA('Payments weekly'!A:A)-1
A13: Payment methods | B13: Payments data warehouse | C13: Methods enabled per merchant, with dates | D13: payment_method_gap | E13: =COUNTA('Payment methods'!A:A)-1
A14: Support tickets | B14: Support desk | C14: Sev-1 tickets | D14: sev1_open | E14: =COUNTA('Support tickets'!A:A)-1
A15: Support weekly | B15: Support desk | C15: Open ticket counts per week | D15: (context) | E15: =COUNTA('Support weekly'!A:A)-1
A16: Gong calls | B16: Gong | C16: Call briefs, attendees, extracted risks/opportunities, sentiment | D16: cross_sell_fit, sentiment_decline, no_contact_90d; contact call history | E16: =COUNTA('Gong calls'!A:A)-1
A17: Slack messages | B17: Slack (shared channels) | C17: Customer messages, classified | D17: contact_departed | E17: =COUNTA('Slack messages'!A:A)-1
A18: NPS responses | B18: NPS survey | C18: Relationship NPS by contact | D18: nps_detractor | E18: =COUNTA('NPS responses'!A:A)-1
A19: Sync log | B19: Ingestion log | C19: Every successful sync per source | D19: freshness → 'data incomplete' badges | E19: =COUNTA('Sync log'!A:A)-1
A20: Source freshness | B20: Computed here | C20: Newest sync and stale flag per source | D20: (formulas) | E20: –
A21: Signals (output) | B21: PriorityOne | C21: What the tracker detected, with history | D21: OUTPUT | E21: =COUNTA('Signals (output)'!A:A)-1
A22: Weekly lists (output) | B22: PriorityOne | C22: This week's scored and ranked accounts | D22: OUTPUT | E22: =COUNTA('Weekly lists (output)'!A:A)-1
A24: Connected tools that don't feed the tracker (Clay enrichment, Looker dashboards) have no tab. Gong is deliberately 12 days stale, which is why some accounts show 'data incomplete'.

Sheet SF Accounts
A1: Account Id | B1: Account Name | C1: Segment | D1: Vertical | E1: Region | F1: ARR (USD) | G1: Customer Since | H1: Account Owner | I1: CSM | J1: Primary Contact | K1: Previous Primary Contact | L1: Contact Changed On | M1: Exec Sponsor Last Contact | N1: Engaged Contacts (90d) | O1: Record URL
A2: 001604FPg2A94Rf | B2: Alder Bazaar | C2: SMB | D2: marketplace | E2: APAC | F2: 122000 | G2: 44352 | H2: Tom Whitaker | I2: David Nakamura | J2: Olivia Rossi | N2: 1 | O2: https://adyen.my.salesforce.com/001604FPg2A94Rf
A3: 0016kz7PLAp9Nh9 | B3: Alder Bites | C3: Mid-Market | D3: food delivery | E3: EMEA | F3: 479000 | G3: 45163 | H3: Lena Fischer | I3: Pedro Silva | J3: Aiko Jansen | N3: 4 | O3: https://adyen.my.salesforce.com/0016kz7PLAp9Nh9
A4: 0016sQhnhNjZAmX | B4: Alder Box | C4: Mid-Market | D4: subscription | E4: EMEA | F4: 640000 | G4: 45319 | H4: Lena Fischer | I4: Yusuf Jansen | J4: Aiko Petrov | N4: 3 | O4: https://adyen.my.salesforce.com/0016sQhnhNjZAmX
A5: 0016ZF3MwRjiDpu | B5: Alder Exchange | C5: Enterprise | D5: marketplace | E5: EMEA | F5: 6996000 | G5: 44404 | H5: Jonas Berg | I5: Rosa Ortega | J5: Chloe Nakamura | M5: 46279 | N5: 3 | O5: https://adyen.my.salesforce.com/0016ZF3MwRjiDpu
A6: 00162BGzhEN5XoA | B6: Alder Market | C6: SMB | D6: marketplace | E6: NA | F6: 117000 | G6: 45817 | H6: Jonas Berg | I6: Zoe Jansen | J6: Ravi Greco | N6: 2 | O6: https://adyen.my.salesforce.com/00162BGzhEN5XoA
A7: 0016NkeJdMTfR6E | B7: Arcturus Gear | C7: Mid-Market | D7: ecommerce | E7: NA | F7: 1973000 | G7: 45652 | H7: Daniel Okafor | I7: Maya Yilmaz | J7: Hugo Greco | N7: 4 | O7: https://adyen.my.salesforce.com/0016NkeJdMTfR6E
A8: 0016mSUYH5MAj9V | B8: Ashgrove Cloud | C8: Enterprise | D8: subscription | E8: NA | F8: 3789000 | G8: 43317 | H8: Priya Raman | I8: Freya Lindqvist | J8: Pedro Nakamura | M8: 46272 | N8: 6 | O8: https://adyen.my.salesforce.com/0016mSUYH5MAj9V
A9: 0016axBUXmySHHN | B9: Ashgrove Eats | C9: SMB | D9: food delivery | E9: NA | F9: 96000 | G9: 44643 | H9: Daniel Okafor | I9: Wen Nakamura | J9: Viktor Quinn | N9: 3 | O9: https://adyen.my.salesforce.com/0016axBUXmySHHN
A10: 0016EoWxnCbxbnQ | B10: Ashgrove Hub | C10: SMB | D10: marketplace | E10: EMEA | F10: 115000 | G10: 45594 | H10: Tom Whitaker | I10: Maya Park | J10: Pedro Castillo | N10: 2 | O10: https://adyen.my.salesforce.com/0016EoWxnCbxbnQ
A11: 00164Hj0Tb00oba | B11: Ashgrove Plus | C11: Mid-Market | D11: subscription | E11: EMEA | F11: 934000 | G11: 44780 | H11: Sofia Marquez | I11: Chloe Quinn | J11: Wen Jansen | N11: 3 | O11: https://adyen.my.salesforce.com/00164Hj0Tb00oba
A12: 0016zEAfqnGEkPi | B12: Bazaarly | C12: SMB | D12: marketplace | E12: EMEA | F12: 214000 | G12: 44923 | H12: Sofia Marquez | I12: Isla Moreau | J12: Olivia Kowalski | N12: 1 | O12: https://adyen.my.salesforce.com/0016zEAfqnGEkPi
A13: 0016rEDjrusmgtv | B13: Bellhaven Delivery | C13: SMB | D13: food delivery | E13: EMEA | F13: 106000 | G13: 44261 | H13: Lena Fischer | I13: Tara Silva | J13: Felix Silva | N13: 2 | O13: https://adyen.my.salesforce.com/0016rEDjrusmgtv
A14: 0016osLuEHLKjXu | B14: Bellhaven Eats | C14: SMB | D14: food delivery | E14: APAC | F14: 115000 | G14: 45783 | H14: Jonas Berg | I14: Jakob Zhou | J14: Viktor Quinn | N14: 1 | O14: https://adyen.my.salesforce.com/0016osLuEHLKjXu
A15: 0016STi5EiELJ6z | B15: Bellhaven Kitchen | C15: Enterprise | D15: food delivery | E15: EMEA | F15: 6893000 | G15: 45598 | H15: Tom Whitaker | I15: Wen Brooks | J15: Hana Greco | M15: 46195 | N15: 3 | O15: https://adyen.my.salesforce.com/0016STi5EiELJ6z
A16: 0016HMShP4zhwFP | B16: Bellhaven Market | C16: Mid-Market | D16: marketplace | E16: EMEA | F16: 437000 | G16: 43575 | H16: Priya Raman | I16: Freya Silva | J16: Olivia Andersen | N16: 5 | O16: https://adyen.my.salesforce.com/0016HMShP4zhwFP
A17: 0016607G0dQM2vj | B17: Bluegate Stays | C17: SMB | D17: travel | E17: APAC | F17: 91000 | G17: 43876 | H17: Sofia Marquez | I17: Maya Hansen | J17: Ravi Zhou | N17: 2 | O17: https://adyen.my.salesforce.com/0016607G0dQM2vj
A18: 0016JUe7vhHBrp2 | B18: Bowlrider | C18: Mid-Market | D18: food delivery | E18: APAC | F18: 1181000 | G18: 43339 | H18: Lena Fischer | I18: Olivia Zhou | J18: Isla Rossi | N18: 1 | O18: https://adyen.my.salesforce.com/0016JUe7vhHBrp2
A19: 0016eRzfnqtaXBh | B19: Brewcrate | C19: SMB | D19: subscription | E19: APAC | F19: 166000 | G19: 43474 | H19: Jonas Berg | I19: Isla Kowalski | J19: Isla Park | N19: 1 | O19: https://adyen.my.salesforce.com/0016eRzfnqtaXBh
A20: 0016TVSQHxNWHyk | B20: Brightline Pharmacy | C20: SMB | D20: retail | E20: EMEA | F20: 184000 | G20: 44158 | H20: Lena Fischer | I20: Aiko Rossi | J20: Zoe Ortega | N20: 1 | O20: https://adyen.my.salesforce.com/0016TVSQHxNWHyk
A21: 0016LW8mWVBmoUK | B21: Brookfield Club | C21: Mid-Market | D21: subscription | E21: EMEA | F21: 432000 | G21: 43774 | H21: Jonas Berg | I21: Kara Lindqvist | J21: Leo Varga | N21: 5 | O21: https://adyen.my.salesforce.com/0016LW8mWVBmoUK
A22: 0016MT5AbVDN746 | B22: Brookfield Delivery | C22: SMB | D22: food delivery | E22: EMEA | F22: 143000 | G22: 43869 | H22: Priya Raman | I22: Olivia Varga | J22: Aiko Zhou | N22: 3 | O22: https://adyen.my.salesforce.com/0016MT5AbVDN746
A23: 0016KR15hvaAxfS | B23: Brookfield Exchange | C23: SMB | D23: marketplace | E23: EMEA | F23: 105000 | G23: 43621 | H23: Lena Fischer | I23: Olivia Brooks | J23: David Quinn | N23: 2 | O23: https://adyen.my.salesforce.com/0016KR15hvaAxfS
A24: 0016dKWKsGBp8oB | B24: Brookfield Market | C24: Mid-Market | D24: marketplace | E24: APAC | F24: 464000 | G24: 44180 | H24: Daniel Okafor | I24: Aiko Rossi | J24: Aiko Rossi | N24: 6 | O24: https://adyen.my.salesforce.com/0016dKWKsGBp8oB
A25: 0016S11rot2NdHk | B25: Cascade Optics | C25: SMB | D25: retail | E25: EMEA | F25: 48000 | G25: 43005 | H25: Priya Raman | I25: Jakob Weber | J25: Yusuf Hansen | N25: 3 | O25: https://adyen.my.salesforce.com/0016S11rot2NdHk
A26: 0016SVY0tPvjvw4 | B26: Cinderleaf Bazaar | C26: SMB | D26: marketplace | E26: APAC | F26: 48000 | G26: 44691 | H26: Daniel Okafor | I26: Kara Nakamura | J26: Chloe Laurent | N26: 3 | O26: https://adyen.my.salesforce.com/0016SVY0tPvjvw4
A27: 0016d9VL1tKxep4 | B27: Cinderleaf Bites | C27: Mid-Market | D27: food delivery | E27: APAC | F27: 988000 | G27: 45742 | H27: Lena Fischer | I27: Noah Varga | J27: Hana Castillo | N27: 4 | O27: https://adyen.my.salesforce.com/0016d9VL1tKxep4
... A42: 00165jLDiF5MEpE | B42: Craftloom | C42: Mid-Market | D42: marketplace | E42: NA | F42: 1285000 | G42: 44616 | H42: Daniel Okafor | I42: Ben Brooks | J42: Rosa Lindqvist | N42: 5 | O42: https://adyen.my.salesforce.com/00165jLDiF5MEpE
A43: 00165LXcvhUtb3z | B43: Dishdash Express | C43: Enterprise | D43: food delivery | E43: NA | F43: 12585000 | G43: 43975 | H43: Daniel Okafor | I43: Leo Nakamura | J43: Yusuf Dubois | M43: 46190 | N43: 6 | O43: https://adyen.my.salesforce.com/00165LXcvhUtb3z
A44: 0016zCyHrzdbcgJ | B44: Dovetail Club | C44: Enterprise | D44: subscription | E44: EMEA | F44: 4356000 | G44: 45225 | H44: Lena Fischer | I44: Omar Park | J44: Ravi Petrov | M44: 46198 | N44: 4 | O44: https://adyen.my.salesforce.com/0016zCyHrzdbcgJ
A45: 0016cvnqjEE5PZK | B45: Dovetail Delivery | C45: SMB | D45: food delivery | E45: EMEA | F45: 62000 | G45: 44191 | H45: Priya Raman | I45: Tara Castillo | J45: Leo Ito | N45: 3 | O45: https://adyen.my.salesforce.com/0016cvnqjEE5PZK
A46: 0016oSP17kqgkiy | B46: Dovetail Exchange | C46: Mid-Market | D46: marketplace | E46: NA | F46: 924000 | G46: 44692 | H46: Priya Raman | I46: Omar Kowalski | J46: Hana Hansen | N46: 6 | O46: https://adyen.my.salesforce.com/0016oSP17kqgkiy
A47: 0016C9zUAVgiFvV | B47: Driftwood Bazaar | C47: Mid-Market | D47: marketplace | E47: NA | F47: 1190000 | G47: 43306 | H47: Tom Whitaker | I47: Omar Bakker | J47: Ravi Andersen | N47: 3 | O47: https://adyen.my.salesforce.com/0016C9zUAVgiFvV
A48: 0016pPQMbUWDjE4 | B48: Driftwood Cloud | C48: Mid-Market | D48: subscription | E48: EMEA | F48: 559000 | G48: 44429 | H48: Tom Whitaker | I48: Pedro Varga | J48: Olivia Dubois | N48: 4 | O48: https://adyen.my.salesforce.com/0016pPQMbUWDjE4
A49: 0016A8JFKLQ8QwG | B49: Driftwood Eats | C49: SMB | D49: food delivery | E49: EMEA | F49: 139000 | G49: 43341 | H49: Lena Fischer | I49: Elena Bakker | J49: Hugo Petrov | N49: 3 | O49: https://adyen.my.salesforce.com/0016A8JFKLQ8QwG
A50: 0016MX7TBxHdPRw | B50: Driftwood Hub | C50: SMB | D50: marketplace | E50: EMEA | F50: 47000 | G50: 45503 | H50: Daniel Okafor | I50: Yusuf Bakker | J50: Viktor Eriksen | N50: 2 | O50: https://adyen.my.salesforce.com/0016MX7TBxHdPRw
A51: 0016URbhtJprNjp | B51: Driftwood Market | C51: SMB | D51: marketplace | E51: NA | F51: 96000 | G51: 45523 | H51: Lena Fischer | I51: Mateo Kowalski | J51: Maya Costa | N51: 3 | O51: https://adyen.my.salesforce.com/0016URbhtJprNjp
A52: 0016T8TJSutz6kM | B52: Driftwood Plus | C52: Mid-Market | D52: subscription | E52: EMEA | F52: 1045000 | G52: 43473 | H52: Priya Raman | I52: David Dubois | J52: Isla Ito | N52: 4 | O52: https://adyen.my.salesforce.com/0016T8TJSutz6kM
A53: 0016UFYqxNFP0nA | B53: Elmstead Bites | C53: Mid-Market | D53: food delivery | E53: NA | F53: 471000 | G53: 44240 | H53: Daniel Okafor | I53: Viktor Ito | J53: Olivia Varga | N53: 5 | O53: https://adyen.my.salesforce.com/0016UFYqxNFP0nA
A54: 0016Qt8f64ouF32 | B54: Elmstead Club | C54: SMB | D54: subscription | E54: APAC | F54: 109000 | G54: 44860 | H54: Lena Fischer | I54: Sam Bakker | J54: Jakob Novak | N54: 1 | O54: https://adyen.my.salesforce.com/0016Qt8f64ouF32
A55: 0016Ke5qZhQmPWQ | B55: Emberly Bites | C55: SMB | D55: food delivery | E55: APAC | F55: 59000 | G55: 44802 | H55: Tom Whitaker | I55: Rosa Moreau | J55: Jakob Lindqvist | N55: 1 | O55: https://adyen.my.salesforce.com/0016Ke5qZhQmPWQ
A56: 0016ZPb11NCd4Xh | B56: Emberly Eats | C56: SMB | D56: food delivery | E56: NA | F56: 152000 | G56: 44331 | H56: Priya Raman | I56: Hana Yilmaz | J56: Anna Ortega | N56: 2 | O56: https://adyen.my.salesforce.com/0016ZPb11NCd4Xh
A57: 0016V5sEEsZWMir | B57: Emberly Exchange | C57: Mid-Market | D57: marketplace | E57: APAC | F57: 985000 | G57: 43452 | H57: Sofia Marquez | I57: Mateo Brooks | J57: Wen Zhou | N57: 4 | O57: https://adyen.my.salesforce.com/0016V5sEEsZWMir
A58: 0016weXTL4FbRuV | B58: Emberly Kitchen | C58: Enterprise | D58: food delivery | E58: NA | F58: 5258000 | G58: 43450 | H58: Daniel Okafor | I58: Kara Varga | J58: David Silva | M58: 46225 | N58: 3 | O58: https://adyen.my.salesforce.com/0016weXTL4FbRuV
A59: 0016wZTpjfmZkxX | B59: Emberly Market | C59: SMB | D59: marketplace | E59: NA | F59: 143000 | G59: 44413 | H59: Priya Raman | I59: Pedro Yilmaz | J59: Freya Andersen | N59: 2 | O59: https://adyen.my.salesforce.com/0016wZTpjfmZkxX
A60: 00161KxwkuucNFP | B60: Emberly Plus | C60: Enterprise | D60: subscription | E60: EMEA | F60: 4829000 | G60: 44486 | H60: Jonas Berg | I60: Wen Moreau | J60: Isla Eriksen | M60: 46173 | N60: 6 | O60: https://adyen.my.salesforce.com/00161KxwkuucNFP
A61: 001693uwSimHWyX | B61: Fablewick Eats | C61: SMB | D61: food delivery | E61: NA | F61: 130000 | G61: 44353 | H61: Lena Fischer | I61: Noah Weber | J61: Omar Kowalski | N61: 1 | O61: https://adyen.my.salesforce.com/001693uwSimHWyX
A62: 0016pWhBHZ742VR | B62: Fernhill Home | C62: Enterprise | D62: ecommerce | E62: EMEA | F62: 5880000 | G62: 45274 | H62: Priya Raman | I62: Leo Zhou | J62: Hana Andersen | M62: 46215 | N62: 6 | O62: https://adyen.my.salesforce.com/0016pWhBHZ742VR
A63: 0016znagAYVza58 | B63: Fitpulse | C63: Mid-Market | D63: subscription | E63: NA | F63: 1092000 | G63: 45053 | H63: Daniel Okafor | I63: Omar Nakamura | J63: Freya Park | N63: 2 | O63: https://adyen.my.salesforce.com/0016znagAYVza58
A64: 0016Mgjse9TModr | B64: Forkfly | C64: SMB | D64: food delivery | E64: NA | F64: 257000 | G64: 43147 | H64: Priya Raman | I64: Omar Ito | J64: Mateo Zhou | N64: 2 | O64: https://adyen.my.salesforce.com/0016Mgjse9TModr
A65: 0016nu9abwNEov4 | B65: Gardenly | C65: Mid-Market | D65: subscription | E65: NA | F65: 1330000 | G65: 45230 | H65: Lena Fischer | I65: Jakob Dubois | J65: Hana Jansen | N65: 2 | O65: https://adyen.my.salesforce.com/0016nu9abwNEov4
A66: 00164kwVq2sjAt3 | B66: Gigforge | C66: Mid-Market | D66: marketplace | E66: EMEA | F66: 751000 | G66: 46075 | H66: Priya Raman | I66: Ravi Hansen | J66: Felix Ortega | N66: 6 | O66: https://adyen.my.salesforce.com/00164kwVq2sjAt3
A67: 0016Jvx5N6a47jH | B67: Glenmoor Box | C67: Mid-Market | D67: subscription | E67: NA | F67: 321000 | G67: 44474 | H67: Tom Whitaker | I67: Jakob Fontaine | J67: Omar Ito | N67: 2 | O67: https://adyen.my.salesforce.com/0016Jvx5N6a47jH
A68: 0016t3FB6jqCsrG | B68: Glenmoor Club | C68: SMB | D68: subscription | E68: EMEA | F68: 119000 | G68: 44840 | H68: Priya Raman | I68: Kara Castillo | J68: Omar Fontaine | N68: 1 | O68: https://adyen.my.salesforce.com/0016t3FB6jqCsrG
A69: 0016ab3gzdy81us | B69: Glenmoor Eats | C69: Mid-Market | D69: food delivery | E69: EMEA | F69: 423000 | G69: 44414 | H69: Sofia Marquez | I69: Chloe Weber | J69: Yusuf Novak | N69: 2 | O69: https://adyen.my.salesforce.com/0016ab3gzdy81us
A70: 0016UxV4ooth6Ke | B70: Grubwagon | C70: Enterprise | D70: food delivery | E70: APAC | F70: 5591000 | G70: 44508 | H70: Tom Whitaker | I70: Hana Bakker | J70: Omar Andersen | M70: 46155 | N70: 6 | O70: https://adyen.my.salesforce.com/0016UxV4ooth6Ke
A71: 0016wdAj2kuxyyt | B71: Halcyon Hotels | C71: SMB | D71: travel | E71: APAC | F71: 244000 | G71: 43417 | H71: Lena Fischer | I71: Rosa Dubois | J71: Isla Brooks | N71: 1 | O71: https://adyen.my.salesforce.com/0016wdAj2kuxyyt
A72: 0016omKdJCVZ816 | B72: Handpicked Hub | C72: Mid-Market | D72: marketplace | E72: NA | F72: 316000 | G72: 43070 | H72: Lena Fischer | I72: Ravi Eriksen | J72: Omar Laurent | N72: 6 | O72: https://adyen.my.salesforce.com/0016omKdJCVZ816
A73: 0016yNY3i37Gyfg | B73: Harborlight Box | C73: SMB | D73: subscription | E73: EMEA | F73: 76000 | G73: 44169 | H73: Priya Raman | I73: Omar Kowalski | J73: Ben Eriksen | N73: 1 | O73: https://adyen.my.salesforce.com/0016yNY3i37Gyfg
A74: 0016HmE776MDT7h | B74: Harborlight Cloud | C74: SMB | D74: subscription | E74: APAC | F74: 156000 | G74: 45714 | H74: Lena Fischer | I74: Felix Silva | J74: Grace Fontaine | N74: 2 | O74: https://adyen.my.salesforce.com/0016HmE776MDT7h
A75: 0016SQNYi9yY9PS | B75: Harborlight Exchange | C75: SMB | D75: marketplace | E75: EMEA | F75: 53000 | G75: 44889 | H75: Sofia Marquez | I75: Omar Eriksen | J75: Viktor Fontaine | N75: 3 | O75: https://adyen.my.salesforce.com/0016SQNYi9yY9PS
A76: 0016FtrVWa6hA3C | B76: Harborlight Hub | C76: SMB | D76: marketplace | E76: NA | F76: 56000 | G76: 44489 | H76: Daniel Okafor | I76: Mateo Quinn | J76: Hugo Petrov | N76: 2 | O76: https://adyen.my.salesforce.com/0016FtrVWa6hA3C
A77: 0016pv7TmAjNFRx | B77: Hartley & Finch | C77: Enterprise | D77: retail | E77: EMEA | F77: 13062000 | G77: 43903 | H77: Lena Fischer | I77: Grace Laurent | J77: Isla Park | M77: 46095 | N77: 6 | O77: https://adyen.my.salesforce.com/0016pv7TmAjNFRx
A78: 00163sKhCJioX6G | B78: Hotbox Delivery | C78: SMB | D78: food delivery | E78: APAC | F78: 51000 | G78: 46033 | H78: Jonas Berg | I78: Hana Bakker | J78: Yusuf Bakker | N78: 1 | O78: https://adyen.my.salesforce.com/00163sKhCJioX6G
A79: 0016DzgfbZtuD4V | B79: Ivorybay Delivery | C79: Mid-Market | D79: food delivery | E79: NA | F79: 675000 | G79: 45463 | H79: Sofia Marquez | I79: Pedro Tanaka | J79: Ravi Nakamura | N79: 3 | O79: https://adyen.my.salesforce.com/0016DzgfbZtuD4V
A80: 00167LN6toyjJkt | B80: Ivorybay Hub | C80: Mid-Market | D80: marketplace | E80: APAC | F80: 905000 | G80: 43305 | H80: Priya Raman | I80: Tara Laurent | J80: Leo Kowalski | N80: 5 | O80: https://adyen.my.salesforce.com/00167LN6toyjJkt
A81: 0016dQc6Rm1B6hm | B81: Ivorybay Kitchen | C81: SMB | D81: food delivery | E81: NA | F81: 134000 | G81: 45775 | H81: Jonas Berg | I81: Jakob Dubois | J81: Nina Ortega | N81: 1 | O81: https://adyen.my.salesforce.com/0016dQc6Rm1B6hm
A82: 0016Wz8eq3x8id4 | B82: Jetwise | C82: Mid-Market | D82: travel | E82: EMEA | F82: 1090000 | G82: 46067 | H82: Jonas Berg | I82: Olivia Eriksen | J82: Sam Tanaka | N82: 2 | O82: https://adyen.my.salesforce.com/0016Wz8eq3x8id4
A83: 0016sgezZLaye70 | B83: Juniper Bazaar | C83: SMB | D83: marketplace | E83: APAC | F83: 144000 | G83: 45625 | H83: Sofia Marquez | I83: Chloe Yilmaz | J83: Aiko Weber | N83: 2 | O83: https://adyen.my.salesforce.com/0016sgezZLaye70
A84: 00162WoNyABBTtg | B84: Juniper Cloud | C84: Mid-Market | D84: subscription | E84: APAC | F84: 512000 | G84: 45140 | H84: Tom Whitaker | I84: Ben Yilmaz | J84: Mateo Ortega | N84: 5 | O84: https://adyen.my.salesforce.com/00162WoNyABBTtg
A85: 0016WL0iRja7kN7 | B85: Juniper Club | C85: Mid-Market | D85: subscription | E85: APAC | F85: 1030000 | G85: 43864 | H85: Daniel Okafor | I85: Tara Nakamura | J85: Maya Eriksen | N85: 2 | O85: https://adyen.my.salesforce.com/0016WL0iRja7kN7
A86: 0016yK8vUhw900p | B86: Juniper Eats | C86: Mid-Market | D86: food delivery | E86: EMEA | F86: 602000 | G86: 43477 | H86: Priya Raman | I86: Ravi Usman | J86: Pedro Greco | N86: 6 | O86: https://adyen.my.salesforce.com/0016yK8vUhw900p
A87: 0016Fw9JJbGc7VE | B87: Juniper Kitchen | C87: SMB | D87: food delivery | E87: APAC | F87: 151000 | G87: 44827 | H87: Sofia Marquez | I87: Olivia Varga | J87: Noah Castillo | N87: 3 | O87: https://adyen.my.salesforce.com/0016Fw9JJbGc7VE
A88: 0016gw3RKdkysXR | B88: Juniper Market | C88: Mid-Market | D88: marketplace | E88: NA | F88: 940000 | G88: 43545 | H88: Jonas Berg | I88: Freya Brooks | J88: Zoe Kowalski | N88: 3 | O88: https://adyen.my.salesforce.com/0016gw3RKdkysXR
A89: 0016ae9eV6odVnq | B89: Kestrel Sports | C89: Enterprise | D89: retail | E89: NA | F89: 14339000 | G89: 44884 | H89: Daniel Okafor | I89: David Rossi | J89: Mateo Quinn | M89: 46254 | N89: 5 | O89: https://adyen.my.salesforce.com/0016ae9eV6odVnq
A90: 0016DJBHzY9Mg7W | B90: Kitefield Bazaar | C90: SMB | D90: marketplace | E90: NA | F90: 65000 | G90: 43674 | H90: Tom Whitaker | I90: David Ito | J90: Yusuf Costa | N90: 2 | O90: https://adyen.my.salesforce.com/0016DJBHzY9Mg7W
A91: 0016fHc7YY4B3qV | B91: Kitefield Bites | C91: SMB | D91: food delivery | E91: NA | F91: 90000 | G91: 44225 | H91: Daniel Okafor | I91: Wen Weber | J91: Hana Quinn | N91: 1 | O91: https://adyen.my.salesforce.com/0016fHc7YY4B3qV
A92: 00165t2t4NE6nbH | B92: Kitefield Eats | C92: Mid-Market | D92: food delivery | E92: EMEA | F92: 747000 | G92: 45790 | H92: Lena Fischer | I92: Yusuf Silva | J92: Ben Petrov | N92: 4 | O92: https://adyen.my.salesforce.com/00165t2t4NE6nbH
A93: 0016ZhvPG8CCXqX | B93: Kitefield Exchange | C93: SMB | D93: marketplace | E93: EMEA | F93: 112000 | G93: 45757 | H93: Sofia Marquez | I93: Ben Lindqvist | J93: Noah Usman | N93: 1 | O93: https://adyen.my.salesforce.com/0016ZhvPG8CCXqX
A94: 0016DxSqJfSFcTE | B94: Larkspur Bazaar | C94: SMB | D94: marketplace | E94: APAC | F94: 143000 | G94: 44661 | H94: Lena Fischer | I94: Ben Brooks | J94: Olivia Eriksen | N94: 3 | O94: https://adyen.my.salesforce.com/0016DxSqJfSFcTE
A95: 00160mwK5KBYJGy | B95: Larkspur Bites | C95: SMB | D95: food delivery | E95: EMEA | F95: 127000 | G95: 45842 | H95: Daniel Okafor | I95: David Yilmaz | J95: Felix Weber | N95: 1 | O95: https://adyen.my.salesforce.com/00160mwK5KBYJGy
A96: 0016CanFGReKjQw | B96: Larkspur Cloud | C96: Mid-Market | D96: subscription | E96: EMEA | F96: 413000 | G96: 43419 | H96: Sofia Marquez | I96: Ravi Eriksen | J96: Freya Tanaka | N96: 5 | O96: https://adyen.my.salesforce.com/0016CanFGReKjQw
A97: 0016w79V2tM8uh1 | B97: Larkspur Club | C97: Enterprise | D97: subscription | E97: EMEA | F97: 6231000 | G97: 45001 | H97: Sofia Marquez | I97: Viktor Moreau | J97: Mateo Kowalski | M97: 46195 | N97: 4 | O97: https://adyen.my.salesforce.com/0016w79V2tM8uh1
A98: 0016EWzhLjzmSR4 | B98: Larkspur Eats | C98: SMB | D98: food delivery | E98: APAC | F98: 42000 | G98: 45609 | H98: Jonas Berg | I98: Elena Usman | J98: Tara Novak | N98: 1 | O98: https://adyen.my.salesforce.com/0016EWzhLjzmSR4
A99: 00161CYkdtZEisX | B99: Learnhive | C99: SMB | D99: subscription | E99: NA | F99: 203000 | G99: 43045 | H99: Jonas Berg | I99: Mateo Jansen | J99: Nina Silva | N99: 1 | O99: https://adyen.my.salesforce.com/00161CYkdtZEisX
A100: 0016MmELAcevpgU | B100: Linden Toys | C100: Mid-Market | D100: retail | E100: NA | F100: 402000 | G100: 45049 | H100: Daniel Okafor | I100: Wen Greco | J100: Felix Hansen | N100: 5 | O100: https://adyen.my.salesforce.com/0016MmELAcevpgU
A101: 00160JrSLyemwdm | B101: Loopsy | C101: Enterprise | D101: marketplace | E101: NA | F101: 5265000 | G101: 45522 | H101: Lena Fischer | I101: Wen Nakamura | J101: Yusuf Andersen | K101: Anna Kowalski | L101: 46281 | M101: 46246 | N101: 4 | O101: https://adyen.my.salesforce.com/00160JrSLyemwdm
A102: 0016m6AuxHu7kzT | B102: Lumen & Lark | C102: Mid-Market | D102: ecommerce | E102: APAC | F102: 1647000 | G102: 43458 | H102: Tom Whitaker | I102: Chloe Moreau | J102: Rosa Ito | N102: 6 | O102: https://adyen.my.salesforce.com/0016m6AuxHu7kzT
A103: 001621vXeTtgyz2 | B103: Mapleton Club | C103: Enterprise | D103: subscription | E103: EMEA | F103: 2791000 | G103: 45153 | H103: Lena Fischer | I103: Mateo Ortega | J103: Anna Ito | M103: 46188 | N103: 4 | O103: https://adyen.my.salesforce.com/001621vXeTtgyz2
A104: 0016BV4VP5ZBzYj | B104: Mapleton Delivery | C104: Mid-Market | D104: food delivery | E104: EMEA | F104: 668000 | G104: 44147 | H104: Priya Raman | I104: Isla Usman | J104: Aiko Lindqvist | N104: 2 | O104: https://adyen.my.salesforce.com/0016BV4VP5ZBzYj
A105: 0016kxaLDK2kaCJ | B105: Mapleton Hub | C105: Mid-Market | D105: marketplace | E105: EMEA | F105: 473000 | G105: 45346 | H105: Jonas Berg | I105: Jakob Fontaine | J105: Ben Nakamura | N105: 2 | O105: https://adyen.my.salesforce.com/0016kxaLDK2kaCJ
A106: 0016tdYdcf6xDus | B106: Marigold Market | C106: SMB | D106: ecommerce | E106: APAC | F106: 228000 | G106: 44905 | H106: Priya Raman | I106: Nina Petrov | J106: David Dubois | N106: 1 | O106: https://adyen.my.salesforce.com/0016tdYdcf6xDus
A107: 0016TdhBaXtu2bx | B107: Meal Atlas | C107: Mid-Market | D107: subscription | E107: APAC | F107: 1921000 | G107: 43696 | H107: Tom Whitaker | I107: Aiko Yilmaz | J107: Pedro Hansen | N107: 4 | O107: https://adyen.my.salesforce.com/0016TdhBaXtu2bx
A108: 0016bhEnruDKK2n | B108: Mosswood Garden Centres | C108: Mid-Market | D108: retail | E108: EMEA | F108: 1049000 | G108: 45690 | H108: Sofia Marquez | I108: Isla Novak | J108: Omar Castillo | N108: 1 | O108: https://adyen.my.salesforce.com/0016bhEnruDKK2n
A109: 0016W6NvRnaQ50c | B109: Munchmile | C109: Enterprise | D109: food delivery | E109: EMEA | F109: 9002000 | G109: 46093 | H109: Priya Raman | I109: Sam Zhou | J109: Olivia Lindqvist | M109: 46231 | N109: 6 | O109: https://adyen.my.salesforce.com/0016W6NvRnaQ50c
A110: 00166i3At6kfcDN | B110: Nibblr | C110: Enterprise | D110: food delivery | E110: APAC | F110: 9151000 | G110: 45540 | H110: Tom Whitaker | I110: Kara Ito | J110: Mateo Moreau | M110: 46222 | N110: 3 | O110: https://adyen.my.salesforce.com/00166i3At6kfcDN
A111: 001681yLtFUitrq | B111: Nomadique | C111: Mid-Market | D111: travel | E111: EMEA | F111: 1331000 | G111: 43996 | H111: Jonas Berg | I111: Olivia Ortega | J111: Pedro Bakker | N111: 3 | O111: https://adyen.my.salesforce.com/001681yLtFUitrq
A112: 0016JihFzD6HKrL | B112: Nordvik Outfitters | C112: Mid-Market | D112: ecommerce | E112: EMEA | F112: 1566000 | G112: 43506 | H112: Tom Whitaker | I112: Noah Park | J112: Leo Hansen | N112: 4 | O112: https://adyen.my.salesforce.com/0016JihFzD6HKrL
A113: 0016r6zhG6AnUgg | B113: Northfield Electronics | C113: Mid-Market | D113: retail | E113: EMEA | F113: 814000 | G113: 46029 | H113: Priya Raman | I113: Ben Brooks | J113: Zoe Eriksen | N113: 4 | O113: https://adyen.my.salesforce.com/0016r6zhG6AnUgg
A114: 0016xmSKhvTjxgJ | B114: Northwind Delivery | C114: Mid-Market | D114: food delivery | E114: APAC | F114: 822000 | G114: 45212 | H114: Jonas Berg | I114: Isla Rossi | J114: Felix Novak | N114: 2 | O114: https://adyen.my.salesforce.com/0016xmSKhvTjxgJ
...

Sheet SF Contacts
A1: Contact Id | B1: Account Id | C1: Account Name | D1: Name | E1: Title | F1: Role (PriorityOne) | G1: Email | H1: Primary Contact | I1: Last Activity | J1: Left Company On | K1: Record URL
A2: 003fiwgwjZxfxB5 | B2: 0016JihFzD6HKrL | C2: Nordvik Outfitters | D2: Leo Hansen | E2: Payments Lead | F2: Day-to-day lead | G2: leo.hansen@nordvikoutfitters.example | H2: Yes | I2: 46183 | K2: https://adyen.my.salesforce.com/003fiwgwjZxfxB5
A3: 003yJS7yDLDZQeN | B3: 0016JihFzD6HKrL | C3: Nordvik Outfitters | D3: Hana Fontaine | E3: Treasury Manager | F3: Finance | G3: hana.fontaine@nordvikoutfitters.example | I3: 46248 | K3: https://adyen.my.salesforce.com/003yJS7yDLDZQeN
A4: 003Yizs5WitbDXT | B4: 0016JihFzD6HKrL | C4: Nordvik Outfitters | D4: Hugo Eriksen | E4: Engineering Manager, Payments | F4: Technical | G4: hugo.eriksen@nordvikoutfitters.example | I4: 46263 | K4: https://adyen.my.salesforce.com/003Yizs5WitbDXT
A5: 003mcaeRt0KzDes | B5: 0016JihFzD6HKrL | C5: Nordvik Outfitters | D5: Elena Castillo | E5: VP E-commerce | F5: Decision maker | G5: elena.castillo@nordvikoutfitters.example | I5: 46274 | K5: https://adyen.my.salesforce.com/003mcaeRt0KzDes
A6: 003CzuG3D0g9bmW | B6: 0016m6AuxHu7kzT | C6: Lumen & Lark | D6: Rosa Ito | E6: Head of Payments | F6: Day-to-day lead | G6: rosa.ito@lumenlark.example | H6: Yes | I6: 46166 | K6: https://adyen.my.salesforce.com/003CzuG3D0g9bmW
A7: 003K39MNkXsZtNg | B7: 0016m6AuxHu7kzT | C7: Lumen & Lark | D7: Ben Moreau | E7: Treasury Manager | F7: Finance | G7: ben.moreau@lumenlark.example | I7: 46283 | K7: https://adyen.my.salesforce.com/003K39MNkXsZtNg
A8: 003YMhNpVGysdEa | B8: 0016m6AuxHu7kzT | C8: Lumen & Lark | D8: Hugo Quinn | E8: Lead Developer, Checkout | F8: Technical | G8: hugo.quinn@lumenlark.example | I8: 46255 | K8: https://adyen.my.salesforce.com/003YMhNpVGysdEa
A9: 003Q3fpRVRN096q | B9: 00167xSizMi9G6r | C9: Cobalt Crate | D9: Anna Yilmaz | E9: Head of Checkout | F9: Day-to-day lead | G9: anna.yilmaz@cobaltcrate.example | H9: Yes | I9: 46169 | K9: https://adyen.my.salesforce.com/003Q3fpRVRN096q
A10: 0034PmXJzMTeWyc | B10: 00167xSizMi9G6r | C10: Cobalt Crate | D10: Noah Hansen | E10: VP Finance | F10: Finance | G10: noah.hansen@cobaltcrate.example | I10: 46280 | K10: https://adyen.my.salesforce.com/0034PmXJzMTeWyc
A11: 003R8nFxrk0aZSN | B11: 0016pWhBHZ742VR | C11: Fernhill Home | D11: Hana Andersen | E11: Head of Payments | F11: Day-to-day lead | G11: hana.andersen@fernhillhome.example | H11: Yes | I11: 46150 | K11: https://adyen.my.salesforce.com/003R8nFxrk0aZSN
A12: 003nqg26tXpLM3m | B12: 0016pWhBHZ742VR | C12: Fernhill Home | D12: Zoe Bakker | E12: CEO | F12: Exec sponsor | G12: zoe.bakker@fernhillhome.example | I12: 46215 | K12: https://adyen.my.salesforce.com/003nqg26tXpLM3m
A13: 003FDskad05Bztd | B13: 0016pWhBHZ742VR | C13: Fernhill Home | D13: Hana Yilmaz | E13: Chief Digital Officer | F13: Decision maker | G13: hana.yilmaz@fernhillhome.example | I13: 46265 | K13: https://adyen.my.salesforce.com/003FDskad05Bztd
A14: 003Kturbt5Pp2ZD | B14: 0016pWhBHZ742VR | C14: Fernhill Home | D14: Sam Ortega | E14: Treasury Manager | F14: Finance | G14: sam.ortega@fernhillhome.example | I14: 46228 | K14: https://adyen.my.salesforce.com/003Kturbt5Pp2ZD
A15: 003mzBipWBXSF6a | B15: 0016pWhBHZ742VR | C15: Fernhill Home | D15: Hugo Ito | E15: Lead Developer, Checkout | F15: Technical | G15: hugo.ito@fernhillhome.example | I15: 46223 | K15: https://adyen.my.salesforce.com/003mzBipWBXSF6a
A16: 003s4CCjbm03ysC | B16: 0016pWhBHZ742VR | C16: Fernhill Home | D16: Zoe Silva | E16: Fraud & Risk Manager | F16: Risk & fraud | G16: zoe.silva@fernhillhome.example | I16: 46285 | K16: https://adyen.my.salesforce.com/003s4CCjbm03ysC
A17: 003ZjGb0ct2A90o | B17: 0016pWhBHZ742VR | C17: Fernhill Home | D17: Yusuf Petrov | E17: Procurement Manager | F17: Procurement | G17: yusuf.petrov@fernhillhome.example | I17: 46241 | K17: https://adyen.my.salesforce.com/003ZjGb0ct2A90o
A18: 0033vyRedJoRpsg | B18: 0016gmLSj6pdPkz | C18: Pebblewave | D18: Elena Varga | E18: Director of E-commerce | F18: Day-to-day lead | G18: elena.varga@pebblewave.example | H18: Yes | I18: 46253 | K18: https://adyen.my.salesforce.com/0033vyRedJoRpsg
A19: 003v9hQJMrTWEXL | B19: 0016gmLSj6pdPkz | C19: Pebblewave | D19: David Laurent | E19: Finance Director | F19: Finance | G19: david.laurent@pebblewave.example | I19: 46290 | K19: https://adyen.my.salesforce.com/003v9hQJMrTWEXL
A20: 003bbErG5222yDG | B20: 0016gmLSj6pdPkz | C20: Pebblewave | D20: Tara Castillo | E20: Lead Developer, Checkout | F20: Technical | G20: tara.castillo@pebblewave.example | I20: 46246 | K20: https://adyen.my.salesforce.com/003bbErG5222yDG
A21: 003VboJzNtHEtf6 | B21: 0016eHRQEXBomQo | C21: Tidewell Apparel | D21: Ravi Quinn | E21: Head of Checkout | F21: Day-to-day lead | G21: ravi.quinn@tidewellapparel.example | H21: Yes | I21: 46173 | K21: https://adyen.my.salesforce.com/003VboJzNtHEtf6
A22: 003MY2q9V2MAJsu | B22: 0016eHRQEXBomQo | C22: Tidewell Apparel | D22: Maya Tanaka | E22: Treasury Manager | F22: Finance | G22: maya.tanaka@tidewellapparel.example | I22: 46281 | K22: https://adyen.my.salesforce.com/003MY2q9V2MAJsu
A23: 003VTi2r4zCBJSS | B23: 0016eHRQEXBomQo | C23: Tidewell Apparel | D23: David Castillo | E23: Lead Developer, Checkout | F23: Technical | G23: david.castillo@tidewellapparel.example | I23: 46227 | K23: https://adyen.my.salesforce.com/003VTi2r4zCBJSS
A24: 003gebquitebtHZ | B24: 0016eHRQEXBomQo | C24: Tidewell Apparel | D24: Tara Eriksen | E24: Chief Digital Officer | F24: Decision maker | G24: tara.eriksen@tidewellapparel.example | I24: 46262 | K24: https://adyen.my.salesforce.com/003gebquitebtHZ
A25: 003wu0WLEYYw6Kh | B25: 00166XEiRTthPkJ | C25: Quillstone Books | D25: Ravi Brooks | E25: Head of Checkout | F25: Day-to-day lead | G25: ravi.brooks@quillstonebooks.example | H25: Yes | I25: 46268 | K25: https://adyen.my.salesforce.com/003wu0WLEYYw6Kh
A26: 003DYhdPYR7LCF5 | B26: 00166XEiRTthPkJ | C26: Quillstone Books | D26: Olivia Kowalski | E26: Operations Manager | F26: Operations | G26: olivia.kowalski@quillstonebooks.example | K26: https://adyen.my.salesforce.com/003DYhdPYR7LCF5
A27: 0038M9Pjn53JXGJ | B27: 0016tdYdcf6xDus | C27: Marigold Market | D27: David Dubois | E27: Director of E-commerce | F27: Day-to-day lead | G27: david.dubois@marigoldmarket.example | H27: Yes | I27: 46237 | K27: https://adyen.my.salesforce.com/0038M9Pjn53JXGJ
A28: 003ZHQW8W24qAU9 | B28: 0016tdYdcf6xDus | C28: Marigold Market | D28: Kara Lindqvist | E28: Finance Director | F28: Finance | G28: kara.lindqvist@marigoldmarket.example | I28: 46168 | K28: https://adyen.my.salesforce.com/003ZHQW8W24qAU9
A29: 003qq9frZSnL14Z | B29: 0016NkeJdMTfR6E | C29: Arcturus Gear | D29: Hugo Greco | E29: Director of E-commerce | F29: Day-to-day lead | G29: hugo.greco@arcturusgear.example | H29: Yes | I29: 46258 | K29: https://adyen.my.salesforce.com/003qq9frZSnL14Z
A30: 003WDvJSeB12kLq | B30: 0016NkeJdMTfR6E | C30: Arcturus Gear | D30: Pedro Ito | E30: Finance Director | F30: Finance | G30: pedro.ito@arcturusgear.example | I30: 46243 | K30: https://adyen.my.salesforce.com/003WDvJSeB12kLq
A31: 0039GtMni68uL6V | B31: 0016NkeJdMTfR6E | C31: Arcturus Gear | D31: Aiko Kowalski | E31: Engineering Manager, Payments | F31: Technical | G31: aiko.kowalski@arcturusgear.example | I31: 46235 | K31: https://adyen.my.salesforce.com/0039GtMni68uL6V
A32: 003ucrc547DQg8G | B32: 0016NkeJdMTfR6E | C32: Arcturus Gear | D32: Sam Eriksen | E32: VP Payments | F32: Decision maker | G32: sam.eriksen@arcturusgear.example | I32: 46236 | K32: https://adyen.my.salesforce.com/003ucrc547DQg8G
A33: 003iJnqk4Lo2MgY | B33: 00165RLchgP6b8D | C33: Velvetine Beauty | D33: Hana Zhou | E33: Director of E-commerce | F33: Day-to-day lead | G33: hana.zhou@velvetinebeauty.example | H33: Yes | I33: 46262 | K33: https://adyen.my.salesforce.com/003iJnqk4Lo2MgY
A34: 003tbVwdXbnFgWP | B34: 00165RLchgP6b8D | C34: Velvetine Beauty | D34: Jakob Lindqvist | E34: Treasury Manager | F34: Finance | G34: jakob.lindqvist@velvetinebeauty.example | I34: 46153 | K34: https://adyen.my.salesforce.com/003tbVwdXbnFgWP
A35: 00368upCd3acSsJ | B35: 00165RLchgP6b8D | C35: Velvetine Beauty | D35: Viktor Bakker | E35: Lead Developer, Checkout | F35: Technical | G35: viktor.bakker@velvetinebeauty.example | I35: 46025 | K35: https://adyen.my.salesforce.com/00368upCd3acSsJ
A36: 003LGhQgFW4BVyf | B36: 00165RLchgP6b8D | C36: Velvetine Beauty | D36: Jakob Yilmaz | E36: VP E-commerce | F36: Decision maker | G36: jakob.yilmaz@velvetinebeauty.example | K36: https://adyen.my.salesforce.com/003LGhQgFW4BVyf
A37: 003pqzz03ugvz32 | B37: 0016x1mtwhKNUPD | C37: Stallbridge | D37: Noah Weber | E37: Head of Checkout | F37: Day-to-day lead | G37: noah.weber@stallbridge.example | H37: Yes | I37: 46212 | K37: https://adyen.my.salesforce.com/003pqzz03ugvz32
A38: 003zHS1GtApYqDr | B38: 0016x1mtwhKNUPD | C38: Stallbridge | D38: Omar Bakker | E38: Chief Operating Officer | F38: Exec sponsor | G38: omar.bakker@stallbridge.example | I38: 46240 | K38: https://adyen.my.salesforce.com/003zHS1GtApYqDr
A39: 003JJGyjSN6tHLb | B39: 0016x1mtwhKNUPD | C39: Stallbridge | D39: Zoe Usman | E39: VP E-commerce | F39: Decision maker | G39: zoe.usman@stallbridge.example | I39: 46277 | K39: https://adyen.my.salesforce.com/003JJGyjSN6tHLb
A40: 0030mSHN9N9QcDG | B40: 0016x1mtwhKNUPD | C40: Stallbridge | D40: Tara Hansen | E40: Treasury Manager | F40: Finance | G40: tara.hansen@stallbridge.example | I40: 46230 | K40: https://adyen.my.salesforce.com/0030mSHN9N9QcDG
A41: 003s79hiSbHLNXr | B41: 0016x1mtwhKNUPD | C41: Stallbridge | D41: Mateo Laurent | E41: Engineering Manager, Payments | F41: Technical | G41: mateo.laurent@stallbridge.example | I41: 46133 | K41: https://adyen.my.salesforce.com/003s79hiSbHLNXr
A42: 003Y0aM7EfLCKEg | B42: 0016x1mtwhKNUPD | C42: Stallbridge | D42: Kara Rossi | E42: Head of Risk | F42: Risk & fraud | G42: kara.rossi@stallbridge.example | I42: 46270 | K42: https://adyen.my.salesforce.com/003Y0aM7EfLCKEg
A43: 0035R1vWvCmpVQ3 | B43: 0016x1mtwhKNUPD | C43: Stallbridge | D43: Ben Kowalski | E43: Procurement Manager | F43: Procurement | G43: ben.kowalski@stallbridge.example | I43: 46230 | K43: https://adyen.my.salesforce.com/0035R1vWvCmpVQ3
A44: 003kaoC9VqsAR4p | B44: 00165jLDiF5MEpE | C44: Craftloom | D44: Rosa Lindqvist | E44: Head of Checkout | F44: Day-to-day lead | G44: rosa.lindqvist@craftloom.example | H44: Yes | I44: 46163 | K44: https://adyen.my.salesforce.com/003kaoC9VqsAR4p
A45: 003qvv3oQFw2YUi | B45: 00165jLDiF5MEpE | C45: Craftloom | D45: Pedro Castillo | E45: Treasury Manager | F45: Finance | G45: pedro.castillo@craftloom.example | I45: 46261 | K45: https://adyen.my.salesforce.com/003qvv3oQFw2YUi
A46: 003zkXSuPhEk4Nb | B46: 00165jLDiF5MEpE | C46: Craftloom | D46: Anna Andersen | E46: Head of Platform | F46: Technical | G46: anna.andersen@craftloom.example | I46: 46288 | K46: https://adyen.my.salesforce.com/003zkXSuPhEk4Nb
A47: 003gfzPj7EPk2hL | B47: 0016CqFctonjWSP | C47: Rentaroo | D47: Tara Tanaka | E47: Payments Lead | F47: Day-to-day lead | G47: tara.tanaka@rentaroo.example | H47: Yes | I47: 46222 | K47: https://adyen.my.salesforce.com/003gfzPj7EPk2hL
A48: 003v5HUTeDnrB7u | B48: 0016CqFctonjWSP | C48: Rentaroo | D48: Omar Park | E48: VP Finance | F48: Finance | G48: omar.park@rentaroo.example | I48: 46254 | K48: https://adyen.my.salesforce.com/003v5HUTeDnrB7u
A49: 0039g8ZZNXZmGzq | B49: 0016CqFctonjWSP | C49: Rentaroo | D49: Chloe Ortega | E49: Engineering Manager, Payments | F49: Technical | G49: chloe.ortega@rentaroo.example | I49: 46192 | K49: https://adyen.my.salesforce.com/0039g8ZZNXZmGzq
A50: 0037mggbBs2zknp | B50: 0016CqFctonjWSP | C50: Rentaroo | D50: Anna Bakker | E50: VP E-commerce | F50: Decision maker | G50: anna.bakker@rentaroo.example | I50: 46262 | K50: https://adyen.my.salesforce.com/0037mggbBs2zknp
A51: 003QrGyNaoaPDb3 | B51: 0016zEAfqnGEkPi | C51: Bazaarly | D51: Olivia Kowalski | E51: Head of Payments | F51: Day-to-day lead | G51: olivia.kowalski@bazaarly.example | H51: Yes | I51: 46209 | K51: https://adyen.my.salesforce.com/003QrGyNaoaPDb3
A52: 003rSZVj8ZQ2pUP | B52: 0016zEAfqnGEkPi | C52: Bazaarly | D52: Elena Fontaine | E52: Head of Operations | F52: Operations | G52: elena.fontaine@bazaarly.example | I52: 46183 | K52: https://adyen.my.salesforce.com/003rSZVj8ZQ2pUP
A53: 003TsPEKFkLvdH7 | B53: 00164kwVq2sjAt3 | C53: Gigforge | D53: Felix Ortega | E53: Head of Payments | F53: Day-to-day lead | G53: felix.ortega@gigforge.example | H53: Yes | I53: 46213 | K53: https://adyen.my.salesforce.com/003TsPEKFkLvdH7
A54: 003CB9mtJ3yYiDg | B54: 00164kwVq2sjAt3 | C54: Gigforge | D54: Felix Dubois | E54: Finance Director | F54: Finance | G54: felix.dubois@gigforge.example | I54: 46227 | K54: https://adyen.my.salesforce.com/003CB9mtJ3yYiDg
A55: 003JH8NGd5j3qPH | B55: 00164kwVq2sjAt3 | C55: Gigforge | D55: Leo Jansen | E55: Engineering Manager, Payments | F55: Technical | G55: leo.jansen@gigforge.example | I55: 46248 | K55: https://adyen.my.salesforce.com/003JH8NGd5j3qPH
A56: 003B8jooL0u1vT1 | B56: 0016pPwXPur5Sih | C56: Tradewind Exchange | D56: Isla Jansen | E56: Director of E-commerce | F56: Day-to-day lead | G56: isla.jansen@tradewindexchange.example | H56: Yes | I56: 46246 | K56: https://adyen.my.salesforce.com/003B8jooL0u1vT1
A57: 003aL2BJ1hGyeXY | B57: 0016pPwXPur5Sih | C57: Tradewind Exchange | D57: Isla Zhou | E57: VP Finance | F57: Finance | G57: isla.zhou@tradewindexchange.example | I57: 46020 | K57: https://adyen.my.salesforce.com/003aL2BJ1hGyeXY
A58: 003KsF9CYV2u25W | B58: 00160JrSLyemwdm | C58: Loopsy | D58: Yusuf Andersen | E58: Head of Checkout | F58: Day-to-day lead | G58: yusuf.andersen@loopsy.example | H58: Yes | I58: 46274 | K58: https://adyen.my.salesforce.com/003KsF9CYV2u25W
A59: 003y3z0FfLAUPiQ | B59: 00160JrSLyemwdm | C59: Loopsy | D59: Anna Kowalski | E59: Payments Lead | F59: Day-to-day lead | G59: anna.kowalski@loopsy.example | I59: 46281 | J59: 46281 | K59: https://adyen.my.salesforce.com/003y3z0FfLAUPiQ
A60: 003bX1JMihXvq4e | B60: 00160JrSLyemwdm | C60: Loopsy | D60: David Eriksen | E60: CFO | F60: Exec sponsor | G60: david.eriksen@loopsy.example | I60: 46246 | K60: https://adyen.my.salesforce.com/003bX1JMihXvq4e
A61: 003U3L878tpdf1J | B61: 00160JrSLyemwdm | C61: Loopsy | D61: Chloe Castillo | E61: VP Payments | F61: Decision maker | G61: chloe.castillo@loopsy.example | I61: 46238 | K61: https://adyen.my.salesforce.com/003U3L878tpdf1J
A62: 0036xiCj7MehACL | B62: 00160JrSLyemwdm | C62: Loopsy | D62: Omar Tanaka | E62: Finance Director | F62: Finance | G62: omar.tanaka@loopsy.example | I62: 46274 | K62: https://adyen.my.salesforce.com/0036xiCj7MehACL
A63: 003FoaG62ijbiib | B63: 00160JrSLyemwdm | C63: Loopsy | D63: Tara Andersen | E63: Lead Developer, Checkout | F63: Technical | G63: tara.andersen@loopsy.example | I63: 46019 | K63: https://adyen.my.salesforce.com/003FoaG62ijbiib
A64: 003FqCsQaGqbPq5 | B64: 00160JrSLyemwdm | C64: Loopsy | D64: Mateo Quinn | E64: Head of Risk | F64: Risk & fraud | G64: mateo.quinn@loopsy.example | K64: https://adyen.my.salesforce.com/003FqCsQaGqbPq5
A65: 003YGNG19KcWHkd | B65: 00160JrSLyemwdm | C65: Loopsy | D65: Hana Ito | E65: Strategic Sourcing Lead | F65: Procurement | G65: hana.ito@loopsy.example | I65: 46286 | K65: https://adyen.my.salesforce.com/003YGNG19KcWHkd
A66: 003aDXDiqnaLyx2 | B66: 0016omKdJCVZ816 | C66: Handpicked Hub | D66: Omar Laurent | E66: Head of Payments | F66: Day-to-day lead | G66: omar.laurent@handpickedhub.example | H66: Yes | I66: 46276 | K66: https://adyen.my.salesforce.com/003aDXDiqnaLyx2
A67: 003Z59s0eiegPo6 | B67: 0016omKdJCVZ816 | C67: Handpicked Hub | D67: Jakob Varga | E67: VP Finance | F67: Finance | G67: jakob.varga@handpickedhub.example | I67: 46264 | K67: https://adyen.my.salesforce.com/003Z59s0eiegPo6
A68: 003CqFNjBh9KWWd | B68: 0016omKdJCVZ816 | C68: Handpicked Hub | D68: Viktor Zhou | E68: Lead Developer, Checkout | F68: Technical | G68: viktor.zhou@handpickedhub.example | I68: 46247 | K68: https://adyen.my.salesforce.com/003CqFNjBh9KWWd
A69: 003g6yFsymREgvS | B69: 0016omKdJCVZ816 | C69: Handpicked Hub | D69: Sam Laurent | E69: Chief Digital Officer | F69: Decision maker | G69: sam.laurent@handpickedhub.example | I69: 46230 | K69: https://adyen.my.salesforce.com/003g6yFsymREgvS
A70: 003hZRyHUFpzbBL | B70: 001676cqyKR6L22 | C70: Swapnest | D70: Mateo Rossi | E70: Head of Operations | F70: Operations | G70: mateo.rossi@swapnest.example | H70: Yes | I70: 46195 | K70: https://adyen.my.salesforce.com/003hZRyHUFpzbBL
A71: 003zSGqCsrhWGfB | B71: 001676cqyKR6L22 | C71: Swapnest | D71: Chloe Dubois | E71: Operations Manager | F71: Operations | G71: chloe.dubois@swapnest.example | I71: 46224 | K71: https://adyen.my.salesforce.com/003zSGqCsrhWGfB
A72: 003Dv9j62g2qJL0 | B72: 00166y2RTL1vGa6 | C72: Vendora | D72: Nina Varga | E72: Head of Payments | F72: Day-to-day lead | G72: nina.varga@vendora.example | H72: Yes | I72: 46180 | K72: https://adyen.my.salesforce.com/003Dv9j62g2qJL0
A73: 003vobexHbnWD5L | B73: 00166y2RTL1vGa6 | C73: Vendora | D73: Ravi Greco | E73: CEO | F73: Exec sponsor | G73: ravi.greco@vendora.example | I73: 46220 | K73: https://adyen.my.salesforce.com/003vobexHbnWD5L
A74: 003z0Eu3s5iM1BC | B74: 00166y2RTL1vGa6 | C74: Vendora | D74: Ben Park | E74: VP E-commerce | F74: Decision maker | G74: ben.park@vendora.example | I74: 46285 | K74: https://adyen.my.salesforce.com/003z0Eu3s5iM1BC
A75: 003gn9Ub7Vpo23P | B75: 00166y2RTL1vGa6 | C75: Vendora | D75: Grace Tanaka | E75: Treasury Manager | F75: Finance | G75: grace.tanaka@vendora.example | I75: 46276 | K75: https://adyen.my.salesforce.com/003gn9Ub7Vpo23P
A76: 003V4iSSB7ngkg3 | B76: 00166y2RTL1vGa6 | C76: Vendora | D76: Olivia Dubois | E76: Engineering Manager, Payments | F76: Technical | G76: olivia.dubois@vendora.example | I76: 46288 | K76: https://adyen.my.salesforce.com/003V4iSSB7ngkg3
A77: 003EGrjt9K78apo | B77: 00166y2RTL1vGa6 | C77: Vendora | D77: Zoe Ito | E77: Fraud & Risk Manager | F77: Risk & fraud | G77: zoe.ito@vendora.example | I77: 46223 | K77: https://adyen.my.salesforce.com/003EGrjt9K78apo
A78: 0039fG8WU8t81rf | B78: 00166y2RTL1vGa6 | C78: Vendora | D78: Zoe Rossi | E78: Procurement Manager | F78: Procurement | G78: zoe.rossi@vendora.example | I78: 46283 | K78: https://adyen.my.salesforce.com/0039fG8WU8t81rf
A79: 003yV7r4EHSN0ph | B79: 001616QQBtNbXT6 | C79: Skyhaven Air | D79: Jakob Costa | E79: Head of Checkout | F79: Day-to-day lead | G79: jakob.costa@skyhavenair.example | H79: Yes | I79: 46196 | K79: https://adyen.my.salesforce.com/003yV7r4EHSN0ph
A80: 00317megFE96EiE | B80: 001616QQBtNbXT6 | C80: Skyhaven Air | D80: Omar Kowalski | E80: Treasury Manager | F80: Finance | G80: omar.kowalski@skyhavenair.example | I80: 46222 | K80: https://adyen.my.salesforce.com/00317megFE96EiE
A81: 0030hED7MQaM9Q7 | B81: 001616QQBtNbXT6 | C81: Skyhaven Air | D81: Felix Costa | E81: Head of Platform | F81: Technical | G81: felix.costa@skyhavenair.example | I81: 46225 | K81: https://adyen.my.salesforce.com/0030hED7MQaM9Q7
A82: 003oqvwdsvmiH77 | B82: 001616QQBtNbXT6 | C82: Skyhaven Air | D82: Pedro Ortega | E82: Chief Digital Officer | F82: Decision maker | G82: pedro.ortega@skyhavenair.example | I82: 46246 | K82: https://adyen.my.salesforce.com/003oqvwdsvmiH77
A83: 0034EiHZ4z64iQh | B83: 00167SMoSCGpdYx | C83: Wayfarer Rail | D83: Anna Dubois | E83: Director of E-commerce | F83: Day-to-day lead | G83: anna.dubois@wayfarerrail.example | H83: Yes | I83: 46201 | K83: https://adyen.my.salesforce.com/0034EiHZ4z64iQh
A84: 003PsGGGYnA88dc | B84: 00167SMoSCGpdYx | C84: Wayfarer Rail | D84: Wen Nakamura | E84: CEO | F84: Exec sponsor | G84: wen.nakamura@wayfarerrail.example | I84: 46072 | K84: https://adyen.my.salesforce.com/003PsGGGYnA88dc
A85: 003xzpGAt6T0iZu | B85: 00167SMoSCGpdYx | C85: Wayfarer Rail | D85: Anna Brooks | E85: VP Payments | F85: Decision maker | G85: anna.brooks@wayfarerrail.example | K85: https://adyen.my.salesforce.com/003xzpGAt6T0iZu
A86: 003LjZQTo04ZeZa | B86: 00167SMoSCGpdYx | C86: Wayfarer Rail | D86: Pedro Varga | E86: Finance Director | F86: Finance | G86: pedro.varga@wayfarerrail.example | I86: 46257 | K86: https://adyen.my.salesforce.com/003LjZQTo04ZeZa
A87: 0034bGMGRK8poPm | B87: 00167SMoSCGpdYx | C87: Wayfarer Rail | D87: Mateo Hansen | E87: Lead Developer, Checkout | F87: Technical | G87: mateo.hansen@wayfarerrail.example | I87: 46263 | K87: https://adyen.my.salesforce.com/0034bGMGRK8poPm
A88: 0039duzWqr60LjF | B88: 00167SMoSCGpdYx | C88: Wayfarer Rail | D88: Jakob Zhou | E88: Fraud & Risk Manager | F88: Risk & fraud | G88: jakob.zhou@wayfarerrail.example | I88: 46236 | K88: https://adyen.my.salesforce.com/0039duzWqr60LjF
A89: 003uRThUGpiip7w | B89: 00167SMoSCGpdYx | C89: Wayfarer Rail | D89: David Ito | E89: Procurement Manager | F89: Procurement | G89: david.ito@wayfarerrail.example | K89: https://adyen.my.salesforce.com/003uRThUGpiip7w
A90: 003ot4fEWtxfChD | B90: 0016wdAj2kuxyyt | C90: Halcyon Hotels | D90: Isla Brooks | E90: Operations Manager | F90: Operations | G90: isla.brooks@halcyonhotels.example | H90: Yes | I90: 46237 | K90: https://adyen.my.salesforce.com/003ot4fEWtxfChD
A91: 003kpkwSocGW1z2 | B91: 0016wdAj2kuxyyt | C91: Halcyon Hotels | D91: Freya Weber | E91: Head of Operations | F91: Operations | G91: freya.weber@halcyonhotels.example | I91: 46039 | K91: https://adyen.my.salesforce.com/003kpkwSocGW1z2
A92: 003GK2c19pTxUe4 | B92: 0016Hx8ViVtcWbv | C92: Orbitra Trips | D92: Yusuf Novak | E92: Payments Lead | F92: Day-to-day lead | G92: yusuf.novak@orbitratrips.example | H92: Yes | I92: 46205 | K92: https://adyen.my.salesforce.com/003GK2c19pTxUe4
A93: 003C0t65kUGNRdH | B93: 0016Hx8ViVtcWbv | C93: Orbitra Trips | D93: Anna Nakamura | E93: Finance Director | F93: Finance | G93: anna.nakamura@orbitratrips.example | I93: 46241 | K93: https://adyen.my.salesforce.com/003C0t65kUGNRdH
A94: 003m6CfHpyRe85g | B94: 0016Hx8ViVtcWbv | C94: Orbitra Trips | D94: Ben Ito | E94: Lead Developer, Checkout | F94: Technical | G94: ben.ito@orbitratrips.example | I94: 45991 | K94: https://adyen.my.salesforce.com/003m6CfHpyRe85g
A95: 003Z9hhzWDg32To | B95: 0016Hx8ViVtcWbv | C95: Orbitra Trips | D95: Sam Jansen | E95: VP Payments | F95: Decision maker | G95: sam.jansen@orbitratrips.example | I95: 46253 | K95: https://adyen.my.salesforce.com/003Z9hhzWDg32To
A96: 003bp0dKY3XE2Dg | B96: 0016Vbm4AVUPd1o | C96: Coastline Ferries | D96: Viktor Silva | E96: Payments Lead | F96: Day-to-day lead | G96: viktor.silva@coastlineferries.example | H96: Yes | I96: 46241 | K96: https://adyen.my.salesforce.com/003bp0dKY3XE2Dg
A97: 003DwonVkeLWWYt | B97: 0016Vbm4AVUPd1o | C97: Coastline Ferries | D97: Wen Weber | E97: Head of Operations | F97: Operations | G97: wen.weber@coastlineferries.example | I97: 46249 | K97: https://adyen.my.salesforce.com/003DwonVkeLWWYt
A98: 003qCHDVtJFDUdq | B98: 001681yLtFUitrq | C98: Nomadique | D98: Pedro Bakker | E98: Head of Checkout | F98: Day-to-day lead | G98: pedro.bakker@nomadique.example | H98: Yes | I98: 46155 | K98: https://adyen.my.salesforce.com/003qCHDVtJFDUdq
A99: 003Xd5PETYwVCE0 | B99: 001681yLtFUitrq | C99: Nomadique | D99: Freya Jansen | E99: Treasury Manager | F99: Finance | G99: freya.jansen@nomadique.example | I99: 46286 | K99: https://adyen.my.salesforce.com/003Xd5PETYwVCE0
A100: 0032LcvJWXdSNcd | B100: 001681yLtFUitrq | C100: Nomadique | D100: Tara Eriksen | E100: Lead Developer, Checkout | F100: Technical | G100: tara.eriksen@nomadique.example | I100: 46285 | K100: https://adyen.my.salesforce.com/0032LcvJWXdSNcd
...

Sheet SF Contracts
A1: Contract Number | B1: Account Id | C1: Account Name | D1: Status | E1: End Date | F1: Days to Renewal
A2: 00000136 | B2: 001604FPg2A94Rf | C2: Alder Bazaar | D2: Activated | E2: 46540 | F2: =E2-'Source freshness'!$B$3
A3: 00000101 | B3: 0016kz7PLAp9Nh9 | C3: Alder Bites | D3: Activated | E3: 46943 | F3: =E3-'Source freshness'!$B$3
A4: 00000103 | B4: 0016sQhnhNjZAmX | C4: Alder Box | D4: Activated | E4: 46459 | F4: =E4-'Source freshness'!$B$3
A5: 00000180 | B5: 0016ZF3MwRjiDpu | C5: Alder Exchange | D5: Activated | E5: 46702 | F5: =E5-'Source freshness'!$B$3
A6: 00000177 | B6: 00162BGzhEN5XoA | C6: Alder Market | D6: Activated | E6: 46714 | F6: =E6-'Source freshness'!$B$3
A7: 00000009 | B7: 0016NkeJdMTfR6E | C7: Arcturus Gear | D7: Activated | E7: 46722 | F7: =E7-'Source freshness'!$B$3
A8: 00000159 | B8: 0016mSUYH5MAj9V | C8: Ashgrove Cloud | D8: Activated | E8: 46832 | F8: =E8-'Source freshness'!$B$3
A9: 00000094 | B9: 0016axBUXmySHHN | C9: Ashgrove Eats | D9: Activated | E9: 46653 | F9: =E9-'Source freshness'!$B$3
A10: 00000121 | B10: 0016EoWxnCbxbnQ | C10: Ashgrove Hub | D10: Activated | E10: 46697 | F10: =E10-'Source freshness'!$B$3
A11: 00000068 | B11: 00164Hj0Tb00oba | C11: Ashgrove Plus | D11: Activated | E11: 46580 | F11: =E11-'Source freshness'!$B$3
A12: 00000014 | B12: 0016zEAfqnGEkPi | C12: Bazaarly | D12: Activated | E12: 46509 | F12: =E12-'Source freshness'!$B$3
A13: 00000104 | B13: 0016rEDjrusmgtv | C13: Bellhaven Delivery | D13: Activated | E13: 46424 | F13: =E13-'Source freshness'!$B$3
... A181: 00000077 | B181: 0016L8o53B1vb8z | C181: Zephyrine Plus | D181: Activated | E181: 46657 | F181: =E181-'Source freshness'!$B$3

Sheet SF QBR Events
A1: Event Id | B1: Account Id | C1: Account Name | D1: Type | E1: Activity Date | F1: Days Since
A2: 00U000136QBR | B2: 001604FPg2A94Rf | C2: Alder Bazaar | D2: QBR | E2: 46246 | F2: ='Source freshness'!$B$3-E2
A3: 00U000101QBR | B3: 0016kz7PLAp9Nh9 | C3: Alder Bites | D3: QBR | E3: 46284 | F3: ='Source freshness'!$B$3-E3
A4: 00U000103QBR | B4: 0016sQhnhNjZAmX | C4: Alder Box | D4: QBR | E4: 46285 | F4: ='Source freshness'!$B$3-E4
A5: 00U000180QBR | B5: 0016ZF3MwRjiDpu | C5: Alder Exchange | D5: QBR | E5: 46216 | F5: ='Source freshness'!$B$3-E5
A6: 00U000177QBR | B6: 00162BGzhEN5XoA | C6: Alder Market | D6: QBR | E6: 46262 | F6: ='Source freshness'!$B$3-E6
A7: 00U000009QBR | B7: 0016NkeJdMTfR6E | C7: Arcturus Gear | D7: QBR | E7: 46258 | F7: ='Source freshness'!$B$3-E7
A8: 00U000159QBR | B8: 0016mSUYH5MAj9V | C8: Ashgrove Cloud | D8: QBR | E8: 46253 | F8: ='Source freshness'!$B$3-E8
A9: 00U000094QBR | B9: 0016axBUXmySHHN | C9: Ashgrove Eats | D9: QBR | E9: 46276 | F9: ='Source freshness'!$B$3-E9
A10: 00U000121QBR | B10: 0016EoWxnCbxbnQ | C10: Ashgrove Hub | D10: QBR | E10: 46225 | F10: ='Source freshness'!$B$3-E10
A11: 00U000068QBR | B11: 00164Hj0Tb00oba | C11: Ashgrove Plus | D11: QBR | E11: 46282 | F11: ='Source freshness'!$B$3-E11
A12: 00U000014QBR | B12: 0016zEAfqnGEkPi | C12: Bazaarly | D12: QBR | E12: 46209 | F12: ='Source freshness'!$B$3-E12
A13: 00U000104QBR | B13: 0016rEDjrusmgtv | C13: Bellhaven Delivery | D13: QBR | E13: 46284 | F13: ='Source freshness'!$B$3-E13
... A181: 00U000077QBR | B181: 0016L8o53B1vb8z | C181: Zephyrine Plus | D181: QBR | E181: 46187 | F181: ='Source freshness'!$B$3-E181

Sheet Payments weekly
A1: Merchant Account | B1: Account Name | C1: Week Start | D1: Processing Volume (USD) | E1: Auth Rate | F1: Chargeback Rate | G1: Failed Payouts
A2: ACC-00001 | B2: Nordvik Outfitters | C2: 46118 | D2: 12079775 | E2: 0.8835 | F2: 0.00549 | G2: 0
A3: ACC-00001 | B3: Nordvik Outfitters | C3: 46125 | D3: 12274914 | E3: 0.8822 | F3: 0.00523 | G3: 0
A4: ACC-00001 | B4: Nordvik Outfitters | C4: 46132 | D4: 12073510 | E4: 0.8755 | F4: 0.00433 | G4: 1
A5: ACC-00001 | B5: Nordvik Outfitters | C5: 46139 | D5: 11716837 | E5: 0.8826 | F5: 0.00455 | G5: 0
A6: ACC-00001 | B6: Nordvik Outfitters | C6: 46146 | D6: 12223129 | E6: 0.8822 | F6: 0.00494 | G6: 0
A7: ACC-00001 | B7: Nordvik Outfitters | C7: 46153 | D7: 12148562 | E7: 0.8871 | F7: 0.00527 | G7: 0
A8: ACC-00001 | B8: Nordvik Outfitters | C8: 46160 | D8: 11869441 | E8: 0.8762 | F8: 0.00492 | G8: 1
A9: ACC-00001 | B9: Nordvik Outfitters | C9: 46167 | D9: 11892436 | E9: 0.8803 | F9: 0.00539 | G9: 0
A10: ACC-00001 | B10: Nordvik Outfitters | C10: 46174 | D10: 11869007 | E10: 0.8795 | F10: 0.00546 | G10: 0
A11: ACC-00001 | B11: Nordvik Outfitters | C11: 46181 | D11: 12013901 | E11: 0.8766 | F11: 0.00527 | G11: 0
A12: ACC-00001 | B12: Nordvik Outfitters | C12: 46188 | D12: 12106589 | E12: 0.8808 | F12: 0.00507 | G12: 0
A13: ACC-00001 | B13: Nordvik Outfitters | C13: 46195 | D13: 11897439 | E13: 0.8809 | F13: 0.00434 | G13: 0
... A4681: ACC-00180 | B4681: Alder Exchange | C4681: 46293 | D4681: 54652176 | E4681: 0.9009 | F4681: 0.0035 | G4681: 0

Sheet Payment methods
A1: Merchant Account | B1: Account Name | C1: Vertical | D1: Payment Method | E1: Enabled On
A2: ACC-00001 | B2: Nordvik Outfitters | C2: ecommerce | D2: Google Pay | E2: 43535
A3: ACC-00001 | B3: Nordvik Outfitters | C3: ecommerce | D3: Apple Pay | E3: 43557
A4: ACC-00001 | B4: Nordvik Outfitters | C4: ecommerce | D4: Cards | E4: 43563
A5: ACC-00001 | B5: Nordvik Outfitters | C5: ecommerce | D5: PayPal | E5: 43563
A6: ACC-00001 | B6: Nordvik Outfitters | C6: ecommerce | D6: Pix | E6: 43712
A7: ACC-00001 | B7: Nordvik Outfitters | C7: ecommerce | D7: Klarna | E7: 45878
A8: ACC-00002 | B8: Lumen & Lark | C8: ecommerce | D8: Cards | E8: 43477
A9: ACC-00002 | B9: Lumen & Lark | C9: ecommerce | D9: Google Pay | E9: 43485
A10: ACC-00002 | B10: Lumen & Lark | C10: ecommerce | D10: Apple Pay | E10: 43498
A11: ACC-00002 | B11: Lumen & Lark | C11: ecommerce | D11: PayPal | E11: 43502
A12: ACC-00003 | B12: Cobalt Crate | C12: ecommerce | D12: Apple Pay | E12: 45450
A13: ACC-00003 | B13: Cobalt Crate | C13: ecommerce | D13: Google Pay | E13: 45459
... A818: ACC-00180 | B818: Alder Exchange | C818: marketplace | D818: Apple Pay | E818: 44450

Sheet Support tickets
A1: Ticket Id | B1: Merchant Account | C1: Account Name | D1: Priority | E1: Opened On | F1: Status | G1: Closed On | H1: Ticket URL
A2: SEV1-39929 | B2: ACC-00024 | C2: Orbitra Trips | D2: Sev-1 | E2: 46279 | F2: Open | H2: https://support.internal.adyen.com/tickets/SEV1-39929
A3: SEV1-11151 | B3: ACC-00009 | C3: Arcturus Gear | D3: Sev-1 | E3: 46286 | F3: Open | H3: https://support.internal.adyen.com/tickets/SEV1-11151
A4: SEV1-29133 | B4: ACC-00034 | C4: Readwell | D4: Sev-1 | E4: 46293 | F4: Open | H4: https://support.internal.adyen.com/tickets/SEV1-29133
A5: SEV1-22597 | B5: ACC-00090 | C5: Sablewood Plus | D5: Sev-1 | E5: 46293 | F5: Open | H5: https://support.internal.adyen.com/tickets/SEV1-22597

Sheet Support weekly
A1: Merchant Account | B1: Account Name | C1: Week Start | D1: Open Tickets | E1: Open Sev-1
A2: ACC-00001 | B2: Nordvik Outfitters | C2: 46118 | D2: 2 | E2: 0
A3: ACC-00001 | B3: Nordvik Outfitters | C3: 46125 | D3: 2 | E3: 0
A4: ACC-00001 | B4: Nordvik Outfitters | C4: 46132 | D4: 2 | E4: 0
A5: ACC-00001 | B5: Nordvik Outfitters | C5: 46139 | D5: 3 | E5: 0
A6: ACC-00001 | B6: Nordvik Outfitters | C6: 46146 | D6: 4 | E6: 0
A7: ACC-00001 | B7: Nordvik Outfitters | C7: 46153 | D7: 3 | E7: 0
A8: ACC-00001 | B8: Nordvik Outfitters | C8: 46160 | D8: 3 | E8: 0
A9: ACC-00001 | B9: Nordvik Outfitters | C9: 46167 | D9: 2 | E9: 0
A10: ACC-00001 | B10: Nordvik Outfitters | C10: 46174 | D10: 1 | E10: 0
A11: ACC-00001 | B11: Nordvik Outfitters | C11: 46181 | D11: 1 | E11: 0
A12: ACC-00001 | B12: Nordvik Outfitters | C12: 46188 | D12: 0 | E12: 0
A13: ACC-00001 | B13: Nordvik Outfitters | C13: 46195 | D13: 0 | E13: 0
... A4681: ACC-00180 | B4681: Alder Exchange | C4681: 46293 | D4681: 1 | E4681: 0

Sheet Gong calls
A1: Call Id | B1: Account Name | C1: Call Date | D1: Attendees | E1: Call Brief | F1: Risks (extracted) | G1: Opportunities (extracted) | H1: Sentiment | I1: Call URL
A2: 1744491610717492151 | B2: Kestrel Sports | C2: 46105 | D2: Mateo Quinn (Director of E-commerce), Noah Varga (VP Finance), Rosa Laurent (Engineering Manager, Payments), Leo Varga (Procurement Manager), Daniel Okafor (AM), David Rossi (CSM) | E2: Working session with Mateo Quinn on their checkout roadmap. Finance raised a question about interchange++ reporting, which we resolved on the call. Agreed to reconvene in four weeks. | G2: Local payment methods in new markets | H2: 0.4 | I2: https://app.gong.io/call?id=1744491610717492151
A3: 3004472094896416487 | B3: Brewcrate | C3: 46106 | D3: Isla Park (Operations Manager), Jonas Berg (AM), Isla Kowalski (CSM) | E3: Call with Isla Park to review last quarter's payments performance. Finance raised a question about interchange++ reporting, which we resolved on the call. Next step: Isla Kowalski to send a follow-up summary and book the next check-in. | G3: Network tokens to lift recurring auth rates | H3: 0.4 | I3: https://app.gong.io/call?id=3004472094896416487
A4: 9622744343259252707 | B4: Nibblr | C4: 46109 | D4: Mateo Moreau (Head of Payments), Aiko Zhou (Chief Digital Officer), Ravi Fontaine (Treasury Manager), Omar Usman (Head of Platform), Hana Ito (Fraud & Risk Manager), Tom Whitaker (AM), Kara Ito (CSM) | E4: Call with Mateo Moreau to review last quarter's payments performance. Integration is stable and they are on a recent API version. Action: share a benchmark of peer auth rates before the next call. | G4: Network tokens to lift recurring auth rates | H4: 0.5 | I4: https://app.gong.io/call?id=9622744343259252707
A5: 9233372370965776416 | B5: Fernhill Home | C5: 46114 | D5: Hana Andersen (Head of Payments), Sam Ortega (Treasury Manager), Yusuf Petrov (Procurement Manager), Priya Raman (AM), Leo Zhou (CSM) | E5: Monthly check-in with Hana Andersen and Leo Zhou. Finance raised a question about interchange++ reporting, which we resolved on the call. Action: share a benchmark of peer auth rates before the next call. | H5: 0.5 | I5: https://app.gong.io/call?id=9233372370965776416
A6: 3680852100028282519 | B6: Fitpulse | C6: 46123 | D6: Freya Park (Head of Checkout), Elena Quinn (Head of Platform), Daniel Okafor (AM), Omar Nakamura (CSM) | E6: Call with Freya Park to review last quarter's payments performance. Volumes are tracking in line with plan and the team is happy with settlement times. Action: share a benchmark of peer auth rates before the next call. | G6: Local payment methods in new markets | H6: 0.4 | I6: https://app.gong.io/call?id=3680852100028282519
A7: 9221459419145169166 | B7: Meal Atlas | C7: 46124 | D7: Pedro Hansen (Payments Lead), Grace Hansen (VP E-commerce), Tom Whitaker (AM), Aiko Yilmaz (CSM) | E7: Call with Pedro Hansen to review last quarter's payments performance. Integration is stable and they are on a recent API version. Agreed to reconvene in four weeks. | G7: Network tokens to lift recurring auth rates | H7: 0.4 | I7: https://app.gong.io/call?id=9221459419145169166
A8: 9867782646728901202 | B8: Nibblr | C8: 46130 | D8: Mateo Moreau (Head of Payments), Ravi Fontaine (Treasury Manager), Tom Whitaker (AM), Kara Ito (CSM) | E8: Working session with Mateo Moreau on their checkout roadmap. Finance raised a question about interchange++ reporting, which we resolved on the call. Agreed to reconvene in four weeks. | H8: 0.5 | I8: https://app.gong.io/call?id=9867782646728901202
A9: 3587539601840277931 | B9: Gigforge | C9: 46134 | D9: Felix Ortega (Head of Payments), Priya Raman (AM), Ravi Hansen (CSM) | E9: Monthly check-in with Felix Ortega and Ravi Hansen. They walked through plans for further growth in Europe over the next two quarters. Action: share a benchmark of peer auth rates before the next call. | H9: 0.6 | I9: https://app.gong.io/call?id=3587539601840277931
A10: 6602720157698976958 | B10: Orbitra Trips | C10: 46140 | D10: Yusuf Novak (Payments Lead), Sofia Marquez (AM), Yusuf Lindqvist (CSM) | E10: Call with Yusuf Novak to review last quarter's payments performance. They walked through plans for further growth in Asia-Pacific over the next two quarters. Action: share a benchmark of peer auth rates before the next call. | H10: 0.2 | I10: https://app.gong.io/call?id=6602720157698976958
A11: 6651713937525836607 | B11: Hotbox Delivery | C11: 46145 | D11: Yusuf Bakker (Payments Lead), Isla Rossi (Treasury Manager), Jonas Berg (AM), Hana Bakker (CSM) | E11: Monthly check-in with Yusuf Bakker and Hana Bakker. They walked through plans for further growth in Asia-Pacific over the next two quarters. Action: share a benchmark of peer auth rates before the next call. | H11: 0.3 | I11: https://app.gong.io/call?id=6651713937525836607
A12: 7423681444277047375 | B12: Craftloom | C12: 46146 | D12: Rosa Lindqvist (Head of Checkout), Anna Andersen (Head of Platform), Daniel Okafor (AM), Ben Brooks (CSM) | E12: Working session with Rosa Lindqvist on their checkout roadmap. Finance raised a question about interchange++ reporting, which we resolved on the call. Next step: Ben Brooks to send a follow-up summary and book the next check-in. | H12: 0.6 | I12: https://app.gong.io/call?id=7423681444277047375
A13: 9022778452343334487 | B13: Vendora | C13: 46146 | D13: Nina Varga (Head of Payments), Tom Whitaker (AM), Felix Yilmaz (CSM) | E13: Monthly check-in with Nina Varga and Felix Yilmaz. Finance raised a question about interchange++ reporting, which we resolved on the call. Action: share a benchmark of peer auth rates before the next call. | H13: 0.5 | I13: https://app.gong.io/call?id=9022778452343334487
A14: 2902851005377343962 | B14: Readwell | C14: 46157 | D14: Tara Silva (Director of E-commerce), Jonas Berg (AM), Viktor Rossi (CSM) | E14: Monthly check-in with Tara Silva and Viktor Rossi. They walked through plans for further growth in Asia-Pacific over the next two quarters. Action: share a benchmark of peer auth rates before the next call. | H14: 0.3 | I14: https://app.gong.io/call?id=2902851005377343962
A15: 1379080347008720580 | B15: Tunebox | C15: 46159 | D15: Hugo Eriksen (Head of Payments), Nina Weber (Treasury Manager), Daniel Okafor (AM), Hugo Greco (CSM) | E15: Working session with Hugo Eriksen on their checkout roadmap. Integration is stable and they are on a recent API version. Agreed to reconvene in four weeks. | H15: 0.5 | I15: https://app.gong.io/call?id=1379080347008720580
A16: 1561378415715004623 | B16: Platepost | C16: 46163 | D16: Olivia Rossi (Head of Payments), Rosa Costa (VP Finance), Jonas Berg (AM), Omar Petrov (CSM) | E16: Monthly check-in with Olivia Rossi and Omar Petrov. Finance raised a question about interchange++ reporting, which we resolved on the call. Action: share a benchmark of peer auth rates before the next call. | H16: 0.3 | I16: https://app.gong.io/call?id=1561378415715004623
A17: 5196889517893545983 | B17: Tunebox | C17: 46164 | D17: Hugo Eriksen (Head of Payments), Rosa Varga (Procurement Manager), Daniel Okafor (AM), Hugo Greco (CSM) | E17: Working session with Hugo Eriksen on their checkout roadmap. Finance raised a question about interchange++ reporting, which we resolved on the call. Next step: Hugo Greco to send a follow-up summary and book the next check-in. | H17: 0.5 | I17: https://app.gong.io/call?id=5196889517893545983
A18: 4621643073317565540 | B18: Spoonwise | C18: 46171 | D18: Chloe Hansen (Director of E-commerce), Jonas Berg (AM), Sam Andersen (CSM) | E18: Working session with Chloe Hansen on their checkout roadmap. Finance raised a question about interchange++ reporting, which we resolved on the call. Next step: Sam Andersen to send a follow-up summary and book the next check-in. | G18: Network tokens to lift recurring auth rates | H18: 0.5 | I18: https://app.gong.io/call?id=4621643073317565540
A19: 2058002530658750772 | B19: Grubwagon | C19: 46171 | D19: Omar Andersen (Head of Checkout), Aiko Novak (Fraud & Risk Manager), Tom Whitaker (AM), Hana Bakker (CSM) | E19: Call with Omar Andersen to review last quarter's payments performance. Volumes are tracking in line with plan and the team is happy with settlement times. Action: share a benchmark of peer auth rates before the next call. | H19: 0.4 | I19: https://app.gong.io/call?id=2058002530658750772
A20: 9362534146265948511 | B20: Sunpath Holidays | C20: 46175 | D20: Isla Zhou (Head of Operations), Priya Raman (AM), Aiko Novak (CSM) | E20: Monthly check-in with Isla Zhou and Aiko Novak. Volumes are tracking in line with plan and the team is happy with settlement times. Action: share a benchmark of peer auth rates before the next call. | G20: Network tokens to lift recurring auth rates | H20: 0.4 | I20: https://app.gong.io/call?id=9362534146265948511
A21: 9299828592171819367 | B21: Sunpath Holidays | C21: 46175 | D21: Isla Zhou (Head of Operations), Priya Raman (AM), Aiko Novak (CSM) | E21: Working session with Isla Zhou on their checkout roadmap. They walked through plans for further growth in Asia-Pacific over the next two quarters. Next step: Aiko Novak to send a follow-up summary and book the next check-in. | G21: Local payment methods in new markets | H21: 0.3 | I21: https://app.gong.io/call?id=9299828592171819367
A22: 3742423433037594340 | B22: Forkfly | C22: 46181 | D22: Mateo Zhou (Head of Checkout), Priya Raman (AM), Omar Ito (CSM) | E22: Monthly check-in with Mateo Zhou and Omar Ito. Finance raised a question about interchange++ reporting, which we resolved on the call. Agreed to reconvene in four weeks. | G22: Local payment methods in new markets | H22: 0.5 | I22: https://app.gong.io/call?id=3742423433037594340
A23: 4255939755978916215 | B23: Gigforge | C23: 46183 | D23: Felix Ortega (Head of Payments), Priya Raman (AM), Ravi Hansen (CSM) | E23: Call with Felix Ortega to review last quarter's payments performance. Integration is stable and they are on a recent API version. Agreed to reconvene in four weeks. | G23: Network tokens to lift recurring auth rates | H23: 0.3 | I23: https://app.gong.io/call?id=4255939755978916215
A24: 7184261304339684611 | B24: Loopsy | C24: 46186 | D24: Anna Kowalski (Payments Lead), Chloe Castillo (VP Payments), Lena Fischer (AM), Wen Nakamura (CSM) | E24: Monthly check-in with Anna Kowalski and Wen Nakamura. Volumes are tracking in line with plan and the team is happy with settlement times. Next step: Wen Nakamura to send a follow-up summary and book the next check-in. | H24: 0.4 | I24: https://app.gong.io/call?id=7184261304339684611
A25: 9069628474489547911 | B25: Spoonwise | C25: 46186 | D25: Chloe Hansen (Director of E-commerce), Jonas Berg (AM), Sam Andersen (CSM) | E25: Monthly check-in with Chloe Hansen and Sam Andersen. Integration is stable and they are on a recent API version. Agreed to reconvene in four weeks. | H25: 0.7 | I25: https://app.gong.io/call?id=9069628474489547911
A26: 9112210897943275978 | B26: Peakline Tours | C26: 46191 | D26: Anna Brooks (Head of Checkout), Lena Fischer (AM), Jakob Hansen (CSM) | E26: Working session with Anna Brooks on their checkout roadmap. Integration is stable and they are on a recent API version. Next step: Jakob Hansen to send a follow-up summary and book the next check-in. | G26: Local payment methods in new markets | H26: 0.5 | I26: https://app.gong.io/call?id=9112210897943275978
A27: 3952598906333732562 | B27: Fernhill Home | C27: 46194 | D27: Hana Andersen (Head of Payments), Hana Yilmaz (Chief Digital Officer), Priya Raman (AM), Leo Zhou (CSM) | E27: Working session with Hana Andersen on their checkout roadmap. Integration is stable and they are on a recent API version. Agreed to reconvene in four weeks. | H27: 0.5 | I27: https://app.gong.io/call?id=3952598906333732562
A28: 4140098286166395290 | B28: Loopsy | C28: 46196 | D28: Anna Kowalski (Payments Lead), Lena Fischer (AM), Wen Nakamura (CSM) | E28: Monthly check-in with Anna Kowalski and Wen Nakamura. Integration is stable and they are on a recent API version. Next step: Wen Nakamura to send a follow-up summary and book the next check-in. | H28: 0.4 | I28: https://app.gong.io/call?id=4140098286166395290
A29: 1152996696145887329 | B29: Vendora | C29: 46197 | D29: Nina Varga (Head of Payments), Tom Whitaker (AM), Felix Yilmaz (CSM) | E29: Working session with Nina Varga on their checkout roadmap. Volumes are tracking in line with plan and the team is happy with settlement times. Action: share a benchmark of peer auth rates before the next call. | G29: Local payment methods in new markets | H29: 0.5 | I29: https://app.gong.io/call?id=1152996696145887329
A30: 6982479686479123043 | B30: Halcyon Hotels | C30: 46198 | D30: Isla Brooks (Operations Manager), Freya Weber (Head of Operations), Lena Fischer (AM), Rosa Dubois (CSM) | E30: Working session with Isla Brooks on their checkout roadmap. Finance raised a question about interchange++ reporting, which we resolved on the call. Agreed to reconvene in four weeks. | G30: Network tokens to lift recurring auth rates | H30: 0.7 | I30: https://app.gong.io/call?id=6982479686479123043
A31: 7089761957880883950 | B31: Brewcrate | C31: 46207 | D31: Isla Park (Operations Manager), Jonas Berg (AM), Isla Kowalski (CSM) | E31: Call with Isla Park to review last quarter's payments performance. Volumes are tracking in line with plan and the team is happy with settlement times. Next step: Isla Kowalski to send a follow-up summary and book the next check-in. | G31: Network tokens to lift recurring auth rates | H31: 0.4 | I31: https://app.gong.io/call?id=7089761957880883950
A32: 2348884663563631456 | B32: Hotbox Delivery | C32: 46207 | D32: Yusuf Bakker (Payments Lead), Isla Rossi (Treasury Manager), Jonas Berg (AM), Hana Bakker (CSM) | E32: Working session with Yusuf Bakker on their checkout roadmap. Integration is stable and they are on a recent API version. Action: share a benchmark of peer auth rates before the next call. | H32: 0.5 | I32: https://app.gong.io/call?id=2348884663563631456
A33: 6875699831471747490 | B33: Kestrel Sports | C33: 46209 | D33: Mateo Quinn (Director of E-commerce), Noah Varga (VP Finance), Rosa Laurent (Engineering Manager, Payments), Leo Varga (Procurement Manager), Daniel Okafor (AM), David Rossi (CSM) | E33: Call with Mateo Quinn to review last quarter's payments performance. They walked through plans for further growth in North America over the next two quarters. Next step: David Rossi to send a follow-up summary and book the next check-in. | G33: Network tokens to lift recurring auth rates | H33: 0.3 | I33: https://app.gong.io/call?id=6875699831471747490
A34: 2884276396621620720 | B34: Grubwagon | C34: 46209 | D34: Omar Andersen (Head of Checkout), Aiko Quinn (Engineering Manager, Payments), Aiko Novak (Fraud & Risk Manager), Tom Whitaker (AM), Hana Bakker (CSM) | E34: Monthly check-in with Omar Andersen and Hana Bakker. Volumes are tracking in line with plan and the team is happy with settlement times. Action: share a benchmark of peer auth rates before the next call. | G34: Local payment methods in new markets | H34: 0.4 | I34: https://app.gong.io/call?id=2884276396621620720
A35: 3526501888814739088 | B35: Readwell | C35: 46212 | D35: Tara Silva (Director of E-commerce), Aiko Silva (VP Finance), Aiko Weber (Head of Platform), Jonas Berg (AM), Viktor Rossi (CSM) | E35: Working session with Tara Silva on their checkout roadmap. Volumes are tracking in line with plan and the team is happy with settlement times. Action: share a benchmark of peer auth rates before the next call. | G35: Network tokens to lift recurring auth rates | H35: 0.3 | I35: https://app.gong.io/call?id=3526501888814739088
A36: 6316479136125298050 | B36: Marigold Market | C36: 46218 | D36: David Dubois (Director of E-commerce), Priya Raman (AM), Nina Petrov (CSM) | E36: Call with David Dubois to review last quarter's payments performance. They walked through plans for further growth in Asia-Pacific over the next two quarters. Action: share a benchmark of peer auth rates before the next call. | H36: 0.5 | I36: https://app.gong.io/call?id=6316479136125298050
A37: 4973875268230024377 | B37: Halcyon Hotels | C37: 46218 | D37: Isla Brooks (Operations Manager), Lena Fischer (AM), Rosa Dubois (CSM) | E37: Monthly check-in with Isla Brooks and Rosa Dubois. Finance raised a question about interchange++ reporting, which we resolved on the call. Next step: Rosa Dubois to send a follow-up summary and book the next check-in. | H37: 0.5 | I37: https://app.gong.io/call?id=4973875268230024377
A38: 7829207077766985137 | B38: Platepost | C38: 46221 | D38: Olivia Rossi (Head of Payments), Rosa Costa (VP Finance), Jonas Berg (AM), Omar Petrov (CSM) | E38: Monthly check-in with Olivia Rossi and Omar Petrov. Volumes are tracking in line with plan and the team is happy with settlement times. Action: share a benchmark of peer auth rates before the next call. | H38: 0.4 | I38: https://app.gong.io/call?id=7829207077766985137
A39: 3087629616994378432 | B39: Rentaroo | C39: 46222 | D39: Tara Tanaka (Payments Lead), Omar Park (VP Finance), Sofia Marquez (AM), David Park (CSM) | E39: Monthly check-in with Tara Tanaka and David Park. Volumes are tracking in line with plan and the team is happy with settlement times. Action: share a benchmark of peer auth rates before the next call. | G39: Network tokens to lift recurring auth rates | H39: 0.2 | I39: https://app.gong.io/call?id=3087629616994378432
A40: 2105895420035335872 | B40: Bazaarly | C40: 46229 | D40: Olivia Kowalski (Head of Payments), Sofia Marquez (AM), Isla Moreau (CSM) | E40: Call with Olivia Kowalski to review last quarter's payments performance. Integration is stable and they are on a recent API version. Next step: Isla Moreau to send a follow-up summary and book the next check-in. | G40: Local payment methods in new markets | H40: 0.6 | I40: https://app.gong.io/call?id=2105895420035335872
A41: 3031499361224243131 | B41: Meal Atlas | C41: 46236 | D41: Pedro Hansen (Payments Lead), Nina Park (Engineering Manager, Payments), Grace Hansen (VP E-commerce), Tom Whitaker (AM), Aiko Yilmaz (CSM) | E41: Working session with Pedro Hansen on their checkout roadmap. Integration is stable and they are on a recent API version. Next step: Aiko Yilmaz to send a follow-up summary and book the next check-in. | G41: Local payment methods in new markets | H41: 0.7 | I41: https://app.gong.io/call?id=3031499361224243131
A42: 6033333171264099570 | B42: Fitpulse | C42: 46237 | D42: Freya Park (Head of Checkout), Maya Brooks (Treasury Manager), Daniel Okafor (AM), Omar Nakamura (CSM) | E42: Working session with Freya Park on their checkout roadmap. Finance raised a question about interchange++ reporting, which we resolved on the call. Action: share a benchmark of peer auth rates before the next call. | H42: 0.3 | I42: https://app.gong.io/call?id=6033333171264099570
A43: 8654017268209796526 | B43: Arcturus Gear | C43: 46239 | D43: Hugo Greco (Director of E-commerce), Daniel Okafor (AM), Maya Yilmaz (CSM) | E43: Working session with Hugo Greco on their checkout roadmap. Volumes are tracking in line with plan and the team is happy with settlement times. Next step: Maya Yilmaz to send a follow-up summary and book the next check-in. | G43: Local payment methods in new markets | H43: 0.5 | I43: https://app.gong.io/call?id=8654017268209796526
A44: 7347905085600815916 | B44: Rentaroo | C44: 46241 | D44: Tara Tanaka (Payments Lead), Anna Bakker (VP E-commerce), Omar Park (VP Finance), Sofia Marquez (AM), David Park (CSM) | E44: Monthly check-in with Tara Tanaka and David Park. Volumes are tracking in line with plan and the team is happy with settlement times. Action: share a benchmark of peer auth rates before the next call. | G44: Network tokens to lift recurring auth rates | H44: 0.3 | I44: https://app.gong.io/call?id=7347905085600815916
A45: 5370311854148542375 | B45: Streamhollow | C45: 46246 | D45: Elena Eriksen (Head of Checkout), Elena Dubois (VP Finance), Isla Hansen (Lead Developer, Checkout), Jonas Berg (AM), Isla Kowalski (CSM) | E45: Call with Elena Eriksen to review last quarter's payments performance. Volumes are tracking in line with plan and the team is happy with settlement times. Action: share a benchmark of peer auth rates before the next call. | G45: Local payment methods in new markets | H45: 0.6 | I45: https://app.gong.io/call?id=5370311854148542375
A46: 8414600695220431383 | B46: Fitpulse | C46: 46248 | D46: Freya Park (Head of Checkout), Maya Brooks (Treasury Manager), Daniel Okafor (AM), Omar Nakamura (CSM) | E46: Monthly check-in with Freya Park and Omar Nakamura. They walked through plans for further growth in North America over the next two quarters. Next step: Omar Nakamura to send a follow-up summary and book the next check-in. | H46: 0.6 | I46: https://app.gong.io/call?id=8414600695220431383
A47: 1931855657516779748 | B47: Coastline Ferries | C47: 46254 | D47: Viktor Silva (Payments Lead), Tom Whitaker (AM), Noah Varga (CSM) | E47: Monthly check-in with Viktor Silva and Noah Varga. Volumes are tracking in line with plan and the team is happy with settlement times. Next step: Noah Varga to send a follow-up summary and book the next check-in. | H47: 0.2 | I47: https://app.gong.io/call?id=1931855657516779748
A48: 9648790566277500696 | B48: Craftloom | C48: 46258 | D48: Rosa Lindqvist (Head of Checkout), Anna Andersen (Head of Platform), Pedro Castillo (Treasury Manager), Daniel Okafor (AM), Ben Brooks (CSM) | E48: Call with Rosa Lindqvist to review last quarter's payments performance. Integration is stable and they are on a recent API version. Next step: Ben Brooks to send a follow-up summary and book the next check-in. | H48: 0.6 | I48: https://app.gong.io/call?id=9648790566277500696
A49: 4081105760693540100 | B49: Sunpath Holidays | C49: 46265 | D49: Isla Zhou (Head of Operations), Priya Raman (AM), Aiko Novak (CSM) | E49: Call with Isla Zhou to review last quarter's payments performance. Isla asked several questions about Adyen Issuing for supplier payouts. They walked through plans for further growth in Asia-Pacific over the next two quarters. Action: share a benchmark of peer auth rates before the next call. | G49: Interest in Adyen Issuing for supplier payouts | H49: 0.6 | I49: https://app.gong.io/call?id=4081105760693540100
A50: 7043977405079144594 | B50: Loopsy | C50: 46266 | D50: Yusuf Andersen (Head of Checkout), Hana Ito (Strategic Sourcing Lead), Omar Tanaka (Finance Director), Lena Fischer (AM), Wen Nakamura (CSM) | E50: Monthly check-in with Yusuf Andersen and Wen Nakamura. Anna Kowalski confirmed they are leaving; Yusuf Andersen will own payments going forward. Finance raised a question about interchange++ reporting, which we resolved on the call. Agreed to reconvene in four weeks. | F50: Champion leaving | H50: 0 | I50: https://app.gong.io/call?id=7043977405079144594
A51: 2123512037852397487 | B51: Grubwagon | C51: 46268 | D51: Omar Andersen (Head of Checkout), Leo Brooks (Finance Director), Aiko Quinn (Engineering Manager, Payments), Hugo Rossi (Chief Digital Officer), Felix Castillo (Procurement Manager), Tom Whitaker (AM), Hana Bakker (CSM) | E51: Monthly check-in with Omar Andersen and Hana Bakker. Omar asked several questions about Terminal API for an in-store pop-up pilot. Integration is stable and they are on a recent API version. Agreed to reconvene in four weeks. | G51: Interest in Terminal API for an in-store pop-up pilot; Network tokens to lift recurring auth rates | H51: 0.2 | I51: https://app.gong.io/call?id=2123512037852397487
A52: 4206349531522106829 | B52: Peakline Tours | C52: 46269 | D52: Anna Brooks (Head of Checkout), Olivia Costa (Procurement Manager), Lena Fischer (AM), Jakob Hansen (CSM) | E52: Working session with Anna Brooks on their checkout roadmap. Anna asked several questions about Adyen Capital for working-capital financing. Finance raised a question about interchange++ reporting, which we resolved on the call. Next step: Jakob Hansen to send a follow-up summary and book the next check-in. | G52: Interest in Adyen Capital for working-capital financing | H52: 0.4 | I52: https://app.gong.io/call?id=4206349531522106829
A53: 7232055038477477484 | B53: Platepost | C53: 46269 | D53: Olivia Ito (Operations Manager), Jonas Berg (AM), Omar Petrov (CSM) | E53: Call with Olivia Ito to review last quarter's payments performance. Olivia mentioned they have started routing part of their Europe traffic to a second acquirer as a 'resilience test'. Olivia Rossi confirmed they are leaving; Olivia Ito will own payments going forward. Next step: Omar Petrov to send a follow-up summary and book the next check-in. | F53: Routing volume to a second acquirer; Champion leaving | H53: 0.2 | I53: https://app.gong.io/call?id=7232055038477477484
A54: 8654423757551447463 | B54: Spoonwise | C54: 46270 | D54: Chloe Hansen (Director of E-commerce), Jonas Berg (AM), Sam Andersen (CSM) | E54: Working session with Chloe Hansen on their checkout roadmap. They flagged more issuer declines since moving their checkout to a new 3DS2 flow. Integration is stable and they are on a recent API version. Next step: Sam Andersen to send a follow-up summary and book the next check-in. | F54: 3DS2 migration hurting conversion | H54: 0 | I54: https://app.gong.io/call?id=8654423757551447463
A55: 3925558262370730355 | B55: Arcturus Gear | C55: 46271 | D55: Hugo Greco (Director of E-commerce), Sam Eriksen (VP Payments), Pedro Ito (Finance Director), Daniel Okafor (AM), Maya Yilmaz (CSM) | E55: Call with Hugo Greco to review last quarter's payments performance. They flagged more issuer declines since moving their checkout to a new 3DS2 flow. They escalated intermittent webhook delays that are holding up order confirmations. Action: share a benchmark of peer auth rates before the next call. | F55: 3DS2 migration hurting conversion; Webhook reliability | H55: 0.2 | I55: https://app.gong.io/call?id=3925558262370730355
A56: 6722899928278892120 | B56: Handpicked Hub | C56: 46272 | D56: Omar Laurent (Head of Payments), Viktor Zhou (Lead Developer, Checkout), Lena Fischer (AM), Ravi Eriksen (CSM) | E56: Monthly check-in with Omar Laurent and Ravi Eriksen. Omar mentioned they have started routing part of their North America traffic to a second acquirer as a 'resilience test'. They walked through plans for further growth in North America over the next two quarters. Agreed to reconvene in four weeks. | F56: Routing volume to a second acquirer | G56: Network tokens to lift recurring auth rates | H56: 0 | I56: https://app.gong.io/call?id=6722899928278892120
A57: 9396287677542649840 | B57: Readwell | C57: 46273 | D57: Tara Silva (Director of E-commerce), Jonas Berg (AM), Viktor Rossi (CSM) | E57: Working session with Tara Silva on their checkout roadmap. They escalated intermittent webhook delays that are holding up order confirmations. Integration is stable and they are on a recent API version. Action: share a benchmark of peer auth rates before the next call. | F57: Webhook reliability | H57: 0 | I57: https://app.gong.io/call?id=9396287677542649840
A58: 3672765131774478358 | B58: Gardenly | C58: 46273 | D58: Hana Jansen (Head of Checkout), Lena Fischer (AM), Jakob Dubois (CSM) | E58: Working session with Hana Jansen on their checkout roadmap. Hana mentioned they have started routing part of their North America traffic to a second acquirer as a 'resilience test'. They walked through plans for further growth in North America over the next two quarters. Next step: Jakob Dubois to send a follow-up summary and book the next check-in. | F58: Routing volume to a second acquirer | H58: 0.1 | I58: https://app.gong.io/call?id=3672765131774478358
A59: 9941781478752482059 | B59: Tunebox | C59: 46276 | D59: Hugo Eriksen (Head of Payments), Nina Weber (Treasury Manager), Hana Ito (Lead Developer, Checkout), Rosa Varga (Procurement Manager), Ravi Eriksen (Fraud & Risk Manager), Daniel Okafor (AM), Hugo Greco (CSM) | E59: Working session with Hugo Eriksen on their checkout roadmap. Hugo mentioned they have started routing part of their North America traffic to a second acquirer as a 'resilience test'. Procurement has joined the account and is asking for a pricing review ahead of the renewal. Agreed to reconvene in four weeks. | F59: Routing volume to a second acquirer; Pricing pressure at renewal | H59: -0.5 | I59: https://app.gong.io/call?id=9941781478752482059
A60: 5630070367634333050 | B60: Brewcrate | C60: 46279 | D60: Isla Park (Operations Manager), Jonas Berg (AM), Isla Kowalski (CSM) | E60: Monthly check-in with Isla Park and Isla Kowalski. Procurement has joined the account and is asking for a pricing review ahead of the renewal. Volumes are tracking in line with plan and the team is happy with settlement times. Agreed to reconvene in four weeks. | F60: Pricing pressure at renewal | G60: Network tokens to lift recurring auth rates | H60: 0 | I60: https://app.gong.io/call?id=5630070367634333050
A61: 9259318201364581268 | B61: Bazaarly | C61: 46280 | D61: Olivia Kowalski (Head of Payments), Sofia Marquez (AM), Isla Moreau (CSM) | E61: Monthly check-in with Olivia Kowalski and Isla Moreau. They launch in two new markets next month and expect volumes to step up. Finance raised a question about interchange++ reporting, which we resolved on the call. Action: share a benchmark of peer auth rates before the next call. | G61: Expansion into new markets | H61: 0.3 | I61: https://app.gong.io/call?id=9259318201364581268
A62: 6332653246667021628 | B62: Cascade Optics | C62: 46280 | D62: Yusuf Hansen (Director of E-commerce), Ben Dubois (Head of Operations), Priya Raman (AM), Jakob Weber (CSM) | E62: Call with Yusuf Hansen to review last quarter's payments performance. They launch in two new markets next month and expect volumes to step up. Finance raised a question about interchange++ reporting, which we resolved on the call. Action: share a benchmark of peer auth rates before the next call. | G62: Expansion into new markets; Network tokens to lift recurring auth rates | H62: 0.3 | I62: https://app.gong.io/call?id=6332653246667021628
A63: 9735869450551161658 | B63: Rentaroo | C63: 46281 | D63: Tara Tanaka (Payments Lead), Anna Bakker (VP E-commerce), Sofia Marquez (AM), David Park (CSM) | E63: Monthly check-in with Tara Tanaka and David Park. They are seeing more friendly-fraud disputes on a new promotion and asked about tightening risk rules. Finance raised a question about interchange++ reporting, which we resolved on the call. Next step: David Park to send a follow-up summary and book the next check-in. | F63: Rising disputes on promotion | G63: RevenueProtect rule tuning | H63: 0.3 | I63: https://app.gong.io/call?id=9735869450551161658
A64: 3531035823902664997 | B64: Fernhill Home | C64: 46282 | D64: Hana Andersen (Head of Payments), Sam Ortega (Treasury Manager), Hugo Ito (Lead Developer, Checkout), Zoe Silva (Fraud & Risk Manager), Hana Yilmaz (Chief Digital Officer), Priya Raman (AM), Leo Zhou (CSM) | E64: Monthly check-in with Hana Andersen and Leo Zhou. Procurement has joined the account and is asking for a pricing review ahead of the renewal. They walked through plans for further growth in Europe over the next two quarters. Agreed to reconvene in four weeks. | F64: Pricing pressure at renewal | G64: Network tokens to lift recurring auth rates | H64: -0.3 | I64: https://app.gong.io/call?id=3531035823902664997
A65: 4246228733431924350 | B65: Vendora | C65: 46282 | D65: Nina Varga (Head of Payments), Zoe Ito (Fraud & Risk Manager), Zoe Rossi (Procurement Manager), Grace Tanaka (Treasury Manager), Ben Park (VP E-commerce), Tom Whitaker (AM), Felix Yilmaz (CSM) | E65: Call with Nina Varga to review last quarter's payments performance. They are seeing more friendly-fraud disputes on a new promotion and asked about tightening risk rules. They walked through plans for further growth in Asia-Pacific over the next two quarters. Action: share a benchmark of peer auth rates before the next call. | F65: Rising disputes on promotion | G65: RevenueProtect rule tuning; Network tokens to lift recurring auth rates | H65: 0.1 | I65: https://app.gong.io/call?id=4246228733431924350
A66: 2024557924229262266 | B66: Orbitra Trips | C66: 46282 | D66: Yusuf Novak (Payments Lead), Anna Nakamura (Finance Director), Sofia Marquez (AM), Yusuf Lindqvist (CSM) | E66: Call with Yusuf Novak to review last quarter's payments performance. They escalated intermittent webhook delays that are holding up order confirmations. Integration is stable and they are on a recent API version. Action: share a benchmark of peer auth rates before the next call. | F66: Webhook reliability | G66: Local payment methods in new markets | H66: 0 | I66: https://app.gong.io/call?id=2024557924229262266
A67: 2296673234321657625 | B67: Nibblr | C67: 46283 | D67: Mateo Moreau (Head of Payments), Ravi Fontaine (Treasury Manager), Rosa Novak (Strategic Sourcing Lead), Tom Whitaker (AM), Kara Ito (CSM) | E67: Call with Mateo Moreau to review last quarter's payments performance. Procurement has joined the account and is asking for a pricing review ahead of the renewal. Integration is stable and they are on a recent API version. Agreed to reconvene in four weeks. | F67: Pricing pressure at renewal | G67: Local payment methods in new markets | H67: 0.1 | I67: https://app.gong.io/call?id=2296673234321657625
A68: 8762785206306407712 | B68: Marigold Market | C68: 46285 | D68: David Dubois (Director of E-commerce), Priya Raman (AM), Nina Petrov (CSM) | E68: Monthly check-in with David Dubois and Nina Petrov. They launch in two new markets next month and expect volumes to step up. Finance raised a question about interchange++ reporting, which we resolved on the call. Agreed to reconvene in four weeks. | G68: Expansion into new markets; Local payment methods in new markets | H68: -0.2 | I68: https://app.gong.io/call?id=8762785206306407712
A69: 9339430113217557601 | B69: Kestrel Sports | C69: 46286 | D69: Mateo Quinn (Director of E-commerce), Noah Varga (VP Finance), Kara Laurent (VP E-commerce), Daniel Okafor (AM), David Rossi (CSM) | E69: Call with Mateo Quinn to review last quarter's payments performance. They flagged more issuer declines since moving their checkout to a new 3DS2 flow. Procurement has joined the account and is asking for a pricing review ahead of the renewal. Agreed to reconvene in four weeks. | F69: 3DS2 migration hurting conversion; Pricing pressure at renewal | H69: 0.3 | I69: https://app.gong.io/call?id=9339430113217557601

Sheet Slack messages
A1: Channel | B1: Account Name | C1: Posted On | D1: Author | E1: Message | F1: Classified As | G1: Feeds Signal
A2: #shared-platepost | B2: Platepost | C2: 46294 | D2: Olivia Rossi (Platepost) | E2: Hi all, today is my last day at Platepost. Olivia Ito will be your contact for payments from now on. Thanks for everything! | F2: Contact change | G2: contact_departed
A3: #shared-cinderleaf-eats | B3: Cinderleaf Eats | C3: 46296 | D3: Yusuf Novak (Cinderleaf Eats) | E3: Can someone confirm when the September settlement report will be ready? | F3: No signal
A4: #shared-handpicked-hub | B4: Handpicked Hub | C4: 46296 | D4: Omar Laurent (Handpicked Hub) | E4: Is there a sandbox we can use to test the new 3DS flow? | F4: No signal
A5: #shared-emberly-market | B5: Emberly Market | C5: 46296 | D5: Freya Andersen (Emberly Market) | E5: Could you re-send the invoice for August? Finance can't find it. | F5: No signal
A6: #shared-cinderleaf-box | B6: Cinderleaf Box | C6: 46296 | D6: Anna Park (Cinderleaf Box) | E6: Quick question on payout timing for the new EUR account. | F6: No signal
A7: #shared-valemont-club | B7: Valemont Club | C7: 46300 | D7: Elena Costa (Valemont Club) | E7: Thanks for the quick fix on the webhook delays yesterday! | F7: No signal
A8: #shared-ashgrove-cloud | B8: Ashgrove Cloud | C8: 46300 | D8: Pedro Nakamura (Ashgrove Cloud) | E8: Heads-up: we launch our autumn promo on Monday, so expect higher volume. | F8: No signal
A9: #shared-forkfly | B9: Forkfly | C9: 46300 | D9: Mateo Zhou (Forkfly) | E9: Great session today, sharing the slides with the team. | F9: No signal
A10: #shared-copperleaf-delivery | B10: Copperleaf Delivery | C10: 46300 | D10: Tara Greco (Copperleaf Delivery) | E10: We'd like to add two more users to the Customer Area. | F10: No signal

Sheet NPS responses
A1: Response Id | B1: Account Name | C1: Respondent | D1: Score (0-10) | E1: Category | F1: Submitted On
A2: NPS-00151-260422 | B2: Mapleton Delivery | C2: Aiko Lindqvist | D2: 9 | E2: =IF(D2>=9,"Promoter",IF(D2>=7,"Passive","Detractor")) | F2: 46134
A3: NPS-00017-260424 | B3: Loopsy | C3: Yusuf Andersen | D3: 7 | E3: =IF(D3>=9,"Promoter",IF(D3>=7,"Passive","Detractor")) | F3: 46136
A4: NPS-00060-260427 | B4: Hotbox Delivery | C4: Yusuf Bakker | D4: 8 | E4: =IF(D4>=9,"Promoter",IF(D4>=7,"Passive","Detractor")) | F4: 46139
A5: NPS-00069-260429 | B5: Ivorybay Delivery | C5: Ravi Nakamura | D5: 7 | E5: =IF(D5>=9,"Promoter",IF(D5>=7,"Passive","Detractor")) | F5: 46141
A6: NPS-00051-260430 | B6: Snackrun | C6: Chloe Tanaka | D6: 9 | E6: =IF(D6>=9,"Promoter",IF(D6>=7,"Passive","Detractor")) | F6: 46142
A7: NPS-00006-260430 | B7: Tidewell Apparel | C7: Ravi Quinn | D7: 7 | E7: =IF(D7>=9,"Promoter",IF(D7>=7,"Passive","Detractor")) | F7: 46142
A8: NPS-00180-260503 | B8: Alder Exchange | C8: Chloe Nakamura | D8: 7 | E8: =IF(D8>=9,"Promoter",IF(D8>=7,"Passive","Detractor")) | F8: 46145
A9: NPS-00158-260503 | B9: Bellhaven Market | C9: Olivia Andersen | D9: 10 | E9: =IF(D9>=9,"Promoter",IF(D9>=7,"Passive","Detractor")) | F9: 46145
A10: NPS-00055-260503 | B10: Bowlrider | C10: Isla Rossi | D10: 7 | E10: =IF(D10>=9,"Promoter",IF(D10>=7,"Passive","Detractor")) | F10: 46145
A11: NPS-00123-260504 | B11: Copperleaf Delivery | C11: Tara Greco | D11: 8 | E11: =IF(D11>=9,"Promoter",IF(D11>=7,"Passive","Detractor")) | F11: 46146
A12: NPS-00144-260504 | B12: Pinecrest Cloud | C12: Nina Tanaka | D12: 10 | E12: =IF(D12>=9,"Promoter",IF(D12>=7,"Passive","Detractor")) | F12: 46146
A13: NPS-00013-260504 | B13: Rentaroo | C13: Tara Tanaka | D13: 9 | E13: =IF(D13>=9,"Promoter",IF(D13>=7,"Passive","Detractor")) | F13: 46146
... A128: NPS-00142-261001 | B128: Copperleaf Kitchen | C128: Elena Lindqvist | D128: 3 | E128: =IF(D128>=9,"Promoter",IF(D128>=7,"Passive","Detractor")) | F128: 46296

Sheet Sync log
A1: Source | B1: Synced On | C1: Rows Synced
A2: gong | B2: 46118 | C2: 110
A3: gong | B3: 46119 | C3: 306
A4: gong | B4: 46120 | C4: 158
A5: gong | B5: 46121 | C5: 196
A6: gong | B6: 46122 | C6: 323
A7: gong | B7: 46123 | C7: 147
A8: gong | B8: 46124 | C8: 102
A9: gong | B9: 46125 | C9: 230
A10: gong | B10: 46126 | C10: 112
A11: gong | B11: 46127 | C11: 58
A12: gong | B12: 46128 | C12: 160
A13: gong | B13: 46129 | C13: 397
... A930: survey | B930: 46297 | C930: 21

Sheet Source freshness
A1: Source freshness
A3: Week being scored (Monday) | B3: 46300 | C3: ← input: change it to check freshness as of another week
A4: A source is stale when its newest sync is more than 7 days before the week being scored.
A6: Source | B6: Newest Sync | C6: Days Behind | D6: Stale? | E6: Feeds
A7: payments_db | B7: =_xlfn.MAXIFS('Sync log'!$B:$B,'Sync log'!$A:$A,A7) | C7: =$B$3-B7 | D7: =IF(C7>7,"Yes","No") | E7: volume, auth rate, chargebacks, payouts, payment methods
A8: salesforce | B8: =_xlfn.MAXIFS('Sync log'!$B:$B,'Sync log'!$A:$A,A8) | C8: =$B$3-B8 | D8: =IF(C8>7,"Yes","No") | E8: renewals, QBRs, contacts, exec sponsor, threading
A9: gong | B9: =_xlfn.MAXIFS('Sync log'!$B:$B,'Sync log'!$A:$A,A9) | C9: =$B$3-B9 | D9: =IF(C9>7,"Yes","No") | E9: call notes, cross-sell, sentiment, no-contact
A10: support | B10: =_xlfn.MAXIFS('Sync log'!$B:$B,'Sync log'!$A:$A,A10) | C10: =$B$3-B10 | D10: =IF(C10>7,"Yes","No") | E10: sev-1 tickets
A11: slack | B11: =_xlfn.MAXIFS('Sync log'!$B:$B,'Sync log'!$A:$A,A11) | C11: =$B$3-B11 | D11: =IF(C11>7,"Yes","No") | E11: contact changes
A12: survey | B12: =_xlfn.MAXIFS('Sync log'!$B:$B,'Sync log'!$A:$A,A12) | C12: =$B$3-B12 | D12: =IF(C12>7,"Yes","No") | E12: NPS

Sheet Signals (output)
A1: Account Name | B1: Signal | C1: Severity | D1: Detected On | E1: Resolved On | F1: Resolution | G1: Source System | H1: Summary | I1: Source Link
A2: Pemberton Shoes | B2: no_contact_90d | C2: low | D2: 46157 | G2: gong | H2: No recorded call or QBR since 13 Feb 2026. | I2: https://app.gong.io/account?crm-id=0016Vpy3n9UeHfv
A3: Learnhive | B3: no_contact_90d | C3: low | D3: 46165 | G3: gong | H3: No recorded call or QBR since 21 Feb 2026. | I3: https://app.gong.io/account?crm-id=00161CYkdtZEisX
A4: Urban Kettle | B4: no_contact_90d | C4: low | D4: 46176 | G4: gong | H4: No recorded call or QBR since 04 Mar 2026. | I4: https://app.gong.io/account?crm-id=0016zjpUG4NUQZM
A5: Petpal Club | B5: no_contact_90d | C5: low | D5: 46187 | G5: gong | H5: No recorded call or QBR since 15 Mar 2026. | I5: https://app.gong.io/account?crm-id=0016dMxjsTq29k0
A6: Snackrun | B6: no_contact_90d | C6: low | D6: 46196 | G6: gong | H6: No recorded call or QBR since 24 Mar 2026. | I6: https://app.gong.io/account?crm-id=0016C7dyWpSBFQu
A7: Gardenly | B7: no_contact_90d | C7: low | D7: 46205 | E7: 46279 | F7: cleared | G7: gong | H7: No recorded call or QBR since 02 Apr 2026. | I7: https://app.gong.io/account?crm-id=0016nu9abwNEov4
A8: Zephyrine Market | B8: no_contact_90d | C8: low | D8: 46231 | G8: gong | H8: No recorded call or QBR since 28 Apr 2026. | I8: https://app.gong.io/account?crm-id=0016X0zw2m5yRn8
A9: Riverbend Hub | B9: no_contact_90d | C9: low | D9: 46232 | G9: gong | H9: No recorded call or QBR since 29 Apr 2026. | I9: https://app.gong.io/account?crm-id=0016w8ej6Zh6qRD
A10: Sablewood Bazaar | B10: no_contact_90d | C10: low | D10: 46240 | G10: gong | H10: No recorded call or QBR since 07 May 2026. | I10: https://app.gong.io/account?crm-id=0016DQXyH5LPVSB
A11: Jetwise | B11: no_contact_90d | C11: low | D11: 46241 | G11: gong | H11: No recorded call or QBR since 08 May 2026. | I11: https://app.gong.io/account?crm-id=0016Wz8eq3x8id4
A12: Willowmere Kitchen | B12: no_contact_90d | C12: low | D12: 46242 | G12: gong | H12: No recorded call or QBR since 09 May 2026. | I12: https://app.gong.io/account?crm-id=0016bDuMhdpjXsY
A13: Cinderleaf Eats | B13: no_contact_90d | C13: low | D13: 46242 | G13: gong | H13: No recorded call or QBR since 09 May 2026. | I13: https://app.gong.io/account?crm-id=00165a3W7X9qvH4
A14: Nomadique | B14: no_contact_90d | C14: low | D14: 46246 | G14: gong | H14: No recorded call or QBR since 13 May 2026. | I14: https://app.gong.io/account?crm-id=001681yLtFUitrq
A15: Pemberton Shoes | B15: qbr_overdue | C15: low | D15: 46247 | G15: salesforce | H15: Last QBR was on 13 Feb 2026, more than 180 days ago. | I15: https://adyen.my.salesforce.com/0016Vpy3n9UeHfv
A16: Cinderleaf Bites | B16: no_contact_90d | C16: low | D16: 46248 | G16: gong | H16: No recorded call or QBR since 15 May 2026. | I16: https://app.gong.io/account?crm-id=0016d9VL1tKxep4
A17: Larkspur Club | B17: no_contact_90d | C17: low | D17: 46249 | G17: gong | H17: No recorded call or QBR since 16 May 2026. | I17: https://app.gong.io/account?crm-id=0016w79V2tM8uh1
A18: Swapnest | B18: volume_drop | C18: medium | D18: 46251 | E18: 46258 | F18: superseded | G18: payments_db | H18: Weekly processing volume fell 25% to $298k, from a $396k baseline. | I18: https://looker.internal.adyen.com/dashboards/merchant-health?account=ACC-00019&metric=volume&week=2026-08-10
A19: Oakmere Department Stores | B19: volume_drop | C19: medium | D19: 46251 | E19: 46258 | F19: superseded | G19: payments_db | H19: Weekly processing volume fell 22% to $865k, from a $1.1M baseline. | I19: https://looker.internal.adyen.com/dashboards/merchant-health?account=ACC-00042&metric=volume&week=2026-08-10
A20: Linden Toys | B20: volume_drop | C20: medium | D20: 46251 | E20: 46265 | F20: cleared | G20: payments_db | H20: Weekly processing volume fell 25% to $2.3M, from a $3.0M baseline. | I20: https://looker.internal.adyen.com/dashboards/merchant-health?account=ACC-00048&metric=volume&week=2026-08-10
A21: Forkfly | B21: volume_drop | C21: medium | D21: 46251 | E21: 46265 | F21: cleared | G21: payments_db | H21: Weekly processing volume fell 26% to $1.5M, from a $2.0M baseline. | I21: https://looker.internal.adyen.com/dashboards/merchant-health?account=ACC-00052&metric=volume&week=2026-08-10
A22: Tunebox | B22: renewal_approaching | C22: medium | D22: 46252 | E22: 46282 | F22: superseded | G22: salesforce | H22: Contract renews on 17 Oct 2026, inside the 60-day window. | I22: https://adyen.my.salesforce.com/0016gtHnPfvS0ZL
A23: Willowmere Plus | B23: no_contact_90d | C23: low | D23: 46252 | G23: gong | H23: No recorded call or QBR since 19 May 2026. | I23: https://app.gong.io/account?crm-id=0016wEnMxMgo5Bn
A24: Wayfarer Rail | B24: exec_sponsor_gap | C24: low | D24: 46253 | G24: salesforce | H24: No executive-level contact since 19 Feb 2026. | I24: https://adyen.my.salesforce.com/00167SMoSCGpdYx
A25: Zephyrine Bites | B25: no_contact_90d | C25: low | D25: 46254 | G25: gong | H25: No recorded call or QBR since 21 May 2026. | I25: https://app.gong.io/account?crm-id=0016mgkZWiJR28z
A26: Learnhive | B26: qbr_overdue | C26: low | D26: 46255 | G26: salesforce | H26: Last QBR was on 21 Feb 2026, more than 180 days ago. | I26: https://adyen.my.salesforce.com/00161CYkdtZEisX
A27: Lumen & Lark | B27: no_contact_90d | C27: low | D27: 46257 | G27: gong | H27: No recorded call or QBR since 24 May 2026. | I27: https://app.gong.io/account?crm-id=0016m6AuxHu7kzT
A28: Quillstone Books | B28: auth_rate_drop | C28: low | D28: 46258 | E28: 46265 | F28: superseded | G28: payments_db | H28: Authorisation rate dropped 4.4 points to 88.8% (was 93.2%). | I28: https://looker.internal.adyen.com/dashboards/merchant-health?account=ACC-00007&metric=auth_rate&week=2026-08-17
A29: Swapnest | B29: volume_drop | C29: high | D29: 46258 | E29: 46265 | F29: cleared | G29: payments_db | H29: Weekly processing volume fell 32% to $268k, from a $396k baseline. | I29: https://looker.internal.adyen.com/dashboards/merchant-health?account=ACC-00019&metric=volume&week=2026-08-17
A30: Bluegate Stays | B30: auth_rate_drop | C30: low | D30: 46258 | E30: 46265 | F30: superseded | G30: payments_db | H30: Authorisation rate dropped 3.9 points to 88.0% (was 92.0%). | I30: https://looker.internal.adyen.com/dashboards/merchant-health?account=ACC-00028&metric=auth_rate&week=2026-08-17
A31: Oakmere Department Stores | B31: volume_drop | C31: high | D31: 46258 | E31: 46265 | F31: cleared | G31: payments_db | H31: Weekly processing volume fell 34% to $734k, from a $1.1M baseline. | I31: https://looker.internal.adyen.com/dashboards/merchant-health?account=ACC-00042&metric=volume&week=2026-08-17
A32: Bellhaven Market | B32: no_contact_90d | C32: low | D32: 46258 | G32: gong | H32: No recorded call or QBR since 25 May 2026. | I32: https://app.gong.io/account?crm-id=0016HMShP4zhwFP
A33: Emberly Exchange | B33: no_contact_90d | C33: low | D33: 46259 | G33: gong | H33: No recorded call or QBR since 26 May 2026. | I33: https://app.gong.io/account?crm-id=0016V5sEEsZWMir
A34: Brookfield Market | B34: no_contact_90d | C34: low | D34: 46259 | G34: gong | H34: No recorded call or QBR since 26 May 2026. | I34: https://app.gong.io/account?crm-id=0016dKWKsGBp8oB
A35: Cobalt Crate | B35: no_contact_90d | C35: low | D35: 46260 | G35: gong | H35: No recorded call or QBR since 27 May 2026. | I35: https://app.gong.io/account?crm-id=00167xSizMi9G6r
A36: Oakmere Department Stores | B36: no_contact_90d | C36: low | D36: 46262 | G36: gong | H36: No recorded call or QBR since 29 May 2026. | I36: https://app.gong.io/account?crm-id=0016FUQbvRVtoZg
A37: Riverbend Club | B37: no_contact_90d | C37: low | D37: 46263 | G37: gong | H37: No recorded call or QBR since 30 May 2026. | I37: https://app.gong.io/account?crm-id=0016Td5YhmsEkjD
A38: Tidewell Apparel | B38: no_contact_90d | C38: low | D38: 46264 | G38: gong | H38: No recorded call or QBR since 31 May 2026. | I38: https://app.gong.io/account?crm-id=0016eHRQEXBomQo
A39: Quillstone Books | B39: auth_rate_drop | C39: medium | D39: 46265 | E39: 46272 | F39: cleared | G39: payments_db | H39: Authorisation rate dropped 7.1 points to 86.1% (was 93.2%). | I39: https://looker.internal.adyen.com/dashboards/merchant-health?account=ACC-00007&metric=auth_rate&week=2026-08-24
A40: Bluegate Stays | B40: auth_rate_drop | C40: medium | D40: 46265 | E40: 46272 | F40: cleared | G40: payments_db | H40: Authorisation rate dropped 7.5 points to 84.5% (was 92.1%). | I40: https://looker.internal.adyen.com/dashboards/merchant-health?account=ACC-00028&metric=auth_rate&week=2026-08-24
A41: Sunpath Holidays | B41: cross_sell_fit | C41: medium | D41: 46265 | G41: gong | H41: On the 31 Aug call the customer mentioned: interest in Adyen Issuing for supplier payouts. | I41: https://app.gong.io/call?id=4081105760693540100
A42: Kestrel Sports | B42: renewal_approaching | C42: medium | D42: 46265 | E42: 46295 | F42: superseded | G42: salesforce | H42: Contract renews on 30 Oct 2026, inside the 60-day window. | I42: https://adyen.my.salesforce.com/0016ae9eV6odVnq
A43: Urban Kettle | B43: qbr_overdue | C43: low | D43: 46266 | G43: salesforce | H43: Last QBR was on 04 Mar 2026, more than 180 days ago. | I43: https://adyen.my.salesforce.com/0016zjpUG4NUQZM
A44: Grubwagon | B44: cross_sell_fit | C44: medium | D44: 46268 | G44: gong | H44: On the 03 Sep call the customer mentioned: interest in Terminal API for an in-store pop-up pilot. | I44: https://app.gong.io/call?id=2123512037852397487
A45: Lumen & Lark | B45: payment_method_gap | C45: medium | D45: 46269 | G45: payments_db | H45: 67% of ecommerce peers offer Klarna; this account does not. | I45: https://looker.internal.adyen.com/dashboards/merchant-health?account=ACC-00002&metric=peer_methods:klarna&week=2026-09-04
A46: Fernhill Home | B46: payment_method_gap | C46: medium | D46: 46269 | E46: 46293 | F46: cleared | G46: payments_db | H46: 67% of ecommerce peers offer Klarna; this account does not. | I46: https://looker.internal.adyen.com/dashboards/merchant-health?account=ACC-00004&metric=peer_methods:klarna&week=2026-09-04
A47: Tidewell Apparel | B47: payment_method_gap | C47: medium | D47: 46269 | E47: 46293 | F47: cleared | G47: payments_db | H47: 67% of ecommerce peers offer Klarna; this account does not. | I47: https://looker.internal.adyen.com/dashboards/merchant-health?account=ACC-00006&metric=peer_methods:klarna&week=2026-09-04
A48: Quillstone Books | B48: payment_method_gap | C48: medium | D48: 46269 | E48: 46300 | F48: cleared | G48: payments_db | H48: 67% of ecommerce peers offer Klarna; this account does not. | I48: https://looker.internal.adyen.com/dashboards/merchant-health?account=ACC-00007&metric=peer_methods:klarna&week=2026-09-04
A49: Peakline Tours | B49: cross_sell_fit | C49: medium | D49: 46269 | G49: gong | H49: On the 04 Sep call the customer mentioned: interest in Adyen Capital for working-capital financing. | I49: https://app.gong.io/call?id=4206349531522106829
A50: Stallbridge | B50: nps_detractor | C50: medium | D50: 46270 | G50: survey | H50: Noah Weber scored us 6/10 in the NPS survey on 05 Sep. | I50: https://survey.internal.adyen.com/nps/ACC-00011
A51: Nordvik Outfitters | B51: no_contact_90d | C51: low | D51: 46274 | G51: gong | H51: No recorded call or QBR since 10 Jun 2026. | I51: https://app.gong.io/account?crm-id=0016JihFzD6HKrL
A52: Opaline Plus | B52: no_contact_90d | C52: low | D52: 46274 | G52: gong | H52: No recorded call or QBR since 10 Jun 2026. | I52: https://app.gong.io/account?crm-id=0016xFru24BUPMG
A53: Glenmoor Box | B53: no_contact_90d | C53: low | D53: 46275 | G53: gong | H53: No recorded call or QBR since 11 Jun 2026. | I53: https://app.gong.io/account?crm-id=0016Jvx5N6a47jH
A54: Wayfarer Rail | B54: payment_method_gap | C54: medium | D54: 46276 | E54: 46293 | F54: cleared | G54: payments_db | H54: 67% of travel peers offer Alipay; this account does not. | I54: https://looker.internal.adyen.com/dashboards/merchant-health?account=ACC-00022&metric=peer_methods:alipay&week=2026-09-11
A55: Halcyon Hotels | B55: payment_method_gap | C55: medium | D55: 46276 | G55: payments_db | H55: 67% of travel peers offer Alipay; this account does not. | I55: https://looker.internal.adyen.com/dashboards/merchant-health?account=ACC-00023&metric=peer_methods:alipay&week=2026-09-11
A56: Nomadique | B56: payment_method_gap | C56: medium | D56: 46276 | E56: 46300 | F56: cleared | G56: payments_db | H56: 67% of travel peers offer Alipay; this account does not. | I56: https://looker.internal.adyen.com/dashboards/merchant-health?account=ACC-00026&metric=peer_methods:alipay&week=2026-09-11
A57: Jetwise | B57: payment_method_gap | C57: medium | D57: 46276 | E57: 46300 | F57: cleared | G57: payments_db | H57: 67% of travel peers offer Alipay; this account does not. | I57: https://looker.internal.adyen.com/dashboards/merchant-health?account=ACC-00029&metric=peer_methods:alipay&week=2026-09-11
A58: Tunebox | B58: sentiment_decline | C58: high | D58: 46276 | G58: gong | H58: Call sentiment fell from +0.5 to -0.5 between the 22 May and 11 Sep calls. | I58: https://app.gong.io/call?id=9941781478752482059
A59: Hartley & Finch | B59: exec_sponsor_gap | C59: low | D59: 46276 | G59: salesforce | H59: No executive-level contact since 14 Mar 2026. | I59: https://adyen.my.salesforce.com/0016pv7TmAjNFRx
A60: Petpal Club | B60: qbr_overdue | C60: low | D60: 46277 | G60: salesforce | H60: Last QBR was on 15 Mar 2026, more than 180 days ago. | I60: https://adyen.my.salesforce.com/0016dMxjsTq29k0
A61: Juniper Cloud | B61: no_contact_90d | C61: low | D61: 46277 | G61: gong | H61: No recorded call or QBR since 13 Jun 2026. | I61: https://app.gong.io/account?crm-id=00162WoNyABBTtg
A62: Brewcrate | B62: renewal_approaching | C62: medium | D62: 46278 | G62: salesforce | H62: Contract renews on 12 Nov 2026, inside the 60-day window. | I62: https://adyen.my.salesforce.com/0016eRzfnqtaXBh
A63: Zephyrine Plus | B63: no_contact_90d | C63: low | D63: 46278 | G63: gong | H63: No recorded call or QBR since 14 Jun 2026. | I63: https://app.gong.io/account?crm-id=0016L8o53B1vb8z
A64: Orbitra Trips | B64: sev1_open | C64: high | D64: 46279 | G64: support | H64: Sev-1 support ticket open since 14 Sep. | I64: https://support.internal.adyen.com/tickets/SEV1-39929
A65: Bowlrider | B65: single_threaded | C65: low | D65: 46280 | G65: salesforce | H65: Single-threaded: only Isla Rossi has engaged with us in the last 90 days. | I65: https://adyen.my.salesforce.com/0016JUe7vhHBrp2
A66: Munchmile | B66: no_contact_90d | C66: low | D66: 46280 | G66: gong | H66: No recorded call or QBR since 16 Jun 2026. | I66: https://app.gong.io/account?crm-id=0016W6NvRnaQ50c
A67: Loopsy | B67: contact_departed | C67: medium | D67: 46281 | G67: salesforce | H67: Primary contact Anna Kowalski has left; Yusuf Andersen is the new contact. | I67: https://adyen.my.salesforce.com/00160JrSLyemwdm
A68: Sablewood Box | B68: no_contact_90d | C68: low | D68: 46281 | G68: gong | H68: No recorded call or QBR since 17 Jun 2026. | I68: https://app.gong.io/account?crm-id=0016jmpLEfkvm9Y
A69: Fernhill Home | B69: sentiment_decline | C69: medium | D69: 46282 | G69: gong | H69: Call sentiment fell from +0.5 to -0.3 between the 21 Jun and 17 Sep calls. | I69: https://app.gong.io/call?id=3531035823902664997
... A78: Swapnest | B78: no_contact_90d | C78: low | D78: 46286 | G78: gong | H78: No recorded call or QBR since 22 Jun 2026. | I78: https://app.gong.io/account?crm-id=001676cqyKR6L22
A79: Tunebox | B79: volume_drop | C79: low | D79: 46286 | E79: 46293 | F79: superseded | G79: payments_db | H79: Weekly processing volume fell 13% to $73.1M, from a $84.5M baseline. | I79: https://looker.internal.adyen.com/dashboards/merchant-health?account=ACC-00036&metric=volume&week=2026-09-14
A80: Gardenly | B80: volume_drop | C80: low | D80: 46286 | E80: 46293 | F80: superseded | G80: payments_db | H80: Weekly processing volume fell 13% to $8.9M, from a $10.3M baseline. | I80: https://looker.internal.adyen.com/dashboards/merchant-health?account=ACC-00037&metric=volume&week=2026-09-14
A81: Brightline Pharmacy | B81: no_contact_90d | C81: low | D81: 46286 | G81: gong | H81: No recorded call or QBR since 22 Jun 2026. | I81: https://app.gong.io/account?crm-id=0016TVSQHxNWHyk
A82: Snackrun | B82: qbr_overdue | C82: low | D82: 46286 | G82: salesforce | H82: Last QBR was on 24 Mar 2026, more than 180 days ago. | I82: https://adyen.my.salesforce.com/0016C7dyWpSBFQu
A83: Forkfly | B83: payment_method_gap | C83: medium | D83: 46286 | E83: 46293 | F83: cleared | G83: payments_db | H83: 92% of food delivery peers offer Google Pay; this account does not. | I83: https://looker.internal.adyen.com/dashboards/merchant-health?account=ACC-00052&metric=peer_methods:google_pay&week=2026-09-21
A84: Dishdash Express | B84: payment_method_gap | C84: medium | D84: 46286 | G84: payments_db | H84: 92% of food delivery peers offer Google Pay; this account does not. | I84: https://looker.internal.adyen.com/dashboards/merchant-health?account=ACC-00053&metric=peer_methods:google_pay&week=2026-09-21
A85: Grubwagon | B85: payment_method_gap | C85: medium | D85: 46286 | E85: 46300 | F85: cleared | G85: payments_db | H85: 92% of food delivery peers offer Google Pay; this account does not. | I85: https://looker.internal.adyen.com/dashboards/merchant-health?account=ACC-00058&metric=peer_methods:google_pay&week=2026-09-21
A86: Munchmile | B86: payment_method_gap | C86: medium | D86: 46286 | E86: 46293 | F86: cleared | G86: payments_db | H86: 92% of food delivery peers offer Google Pay; this account does not. | I86: https://looker.internal.adyen.com/dashboards/merchant-health?account=ACC-00059&metric=peer_methods:google_pay&week=2026-09-21
A87: Hotbox Delivery | B87: payment_method_gap | C87: medium | D87: 46286 | E87: 46300 | F87: cleared | G87: payments_db | H87: 92% of food delivery peers offer Google Pay; this account does not. | I87: https://looker.internal.adyen.com/dashboards/merchant-health?account=ACC-00060&metric=peer_methods:google_pay&week=2026-09-21
A88: Fernhill Home | B88: renewal_approaching | C88: medium | D88: 46287 | G88: salesforce | H88: Contract renews on 21 Nov 2026, inside the 60-day window. | I88: https://adyen.my.salesforce.com/0016pWhBHZ742VR
A89: Skyhaven Air | B89: no_contact_90d | C89: low | D89: 46287 | G89: gong | H89: No recorded call or QBR since 23 Jun 2026. | I89: https://app.gong.io/account?crm-id=001616QQBtNbXT6
A90: Fitpulse | B90: payment_method_gap | C90: medium | D90: 46289 | E90: 46300 | F90: cleared | G90: payments_db | H90: 94% of subscription peers offer PayPal; this account does not. | I90: https://looker.internal.adyen.com/dashboards/merchant-health?account=ACC-00032&metric=peer_methods:paypal&week=2026-09-24
A91: Meal Atlas | B91: payment_method_gap | C91: medium | D91: 46289 | G91: payments_db | H91: 94% of subscription peers offer PayPal; this account does not. | I91: https://looker.internal.adyen.com/dashboards/merchant-health?account=ACC-00033&metric=peer_methods:paypal&week=2026-09-24
A92: Readwell | B92: payment_method_gap | C92: medium | D92: 46289 | E92: 46300 | F92: cleared | G92: payments_db | H92: 94% of subscription peers offer PayPal; this account does not. | I92: https://looker.internal.adyen.com/dashboards/merchant-health?account=ACC-00034&metric=peer_methods:paypal&week=2026-09-24
A93: Petpal Club | B93: payment_method_gap | C93: medium | D93: 46289 | E93: 46300 | F93: cleared | G93: payments_db | H93: 94% of subscription peers offer PayPal; this account does not. | I93: https://looker.internal.adyen.com/dashboards/merchant-health?account=ACC-00039&metric=peer_methods:paypal&week=2026-09-24
A94: Hartley & Finch | B94: no_contact_90d | C94: low | D94: 46289 | G94: gong | H94: No recorded call or QBR since 25 Jun 2026. | I94: https://app.gong.io/account?crm-id=0016pv7TmAjNFRx
A95: Nibblr | B95: nps_detractor | C95: medium | D95: 46291 | G95: survey | H95: Mateo Moreau scored us 5/10 in the NPS survey on 26 Sep. | I95: https://survey.internal.adyen.com/nps/ACC-00054
A96: Wayfarer Rail | B96: no_contact_90d | C96: low | D96: 46292 | G96: gong | H96: No recorded call or QBR since 28 Jun 2026. | I96: https://app.gong.io/account?crm-id=00167SMoSCGpdYx
A97: Marigold Market | B97: volume_growth | C97: medium | D97: 46293 | E97: 46300 | F97: superseded | G97: payments_db | H97: Weekly processing volume grew 29% to $2.4M, from a $1.8M baseline. | I97: https://looker.internal.adyen.com/dashboards/merchant-health?account=ACC-00008&metric=volume&week=2026-09-21
A98: Arcturus Gear | B98: auth_rate_drop | C98: low | D98: 46293 | E98: 46300 | F98: superseded | G98: payments_db | H98: Authorisation rate dropped 3.3 points to 84.6% (was 87.9%). | I98: https://looker.internal.adyen.com/dashboards/merchant-health?account=ACC-00009&metric=auth_rate&week=2026-09-21
A99: Rentaroo | B99: chargeback_spike | C99: medium | D99: 46293 | E99: 46300 | F99: superseded | G99: payments_db | H99: Chargeback rate hit 1.05% (was 0.47%), above typical card-scheme monitoring thresholds (~0.9%). | I99: https://looker.internal.adyen.com/dashboards/merchant-health?account=ACC-00013&metric=chargebacks&week=2026-09-21
A100: Handpicked Hub | B100: volume_drop | C100: low | D100: 46293 | E100: 46300 | F100: superseded | G100: payments_db | H100: Weekly processing volume fell 17% to $2.0M, from a $2.5M baseline. | I100: https://looker.internal.adyen.com/dashboards/merchant-health?account=ACC-00018&metric=volume&week=2026-09-21
A101: Vendora | B101: chargeback_spike | C101: medium | D101: 46293 | E101: 46300 | F101: superseded | G101: payments_db | H101: Chargeback rate hit 0.95% (was 0.23%), above typical card-scheme monitoring thresholds (~0.9%). | I101: https://looker.internal.adyen.com/dashboards/merchant-health?account=ACC-00020&metric=chargebacks&week=2026-09-21
A102: Readwell | B102: sev1_open | C102: high | D102: 46293 | G102: support | H102: Sev-1 support ticket open since 28 Sep. | I102: https://support.internal.adyen.com/tickets/SEV1-29133
A103: Tunebox | B103: volume_drop | C103: medium | D103: 46293 | E103: 46300 | F103: superseded | G103: payments_db | H103: Weekly processing volume fell 23% to $64.6M, from a $84.0M baseline. | I103: https://looker.internal.adyen.com/dashboards/merchant-health?account=ACC-00036&metric=volume&week=2026-09-21
A104: Gardenly | B104: volume_drop | C104: medium | D104: 46293 | E104: 46300 | F104: superseded | G104: payments_db | H104: Weekly processing volume fell 23% to $7.9M, from a $10.2M baseline. | I104: https://looker.internal.adyen.com/dashboards/merchant-health?account=ACC-00037&metric=volume&week=2026-09-21
A105: Kestrel Sports | B105: auth_rate_drop | C105: low | D105: 46293 | E105: 46300 | F105: superseded | G105: payments_db | H105: Authorisation rate dropped 3.5 points to 86.9% (was 90.4%). | I105: https://looker.internal.adyen.com/dashboards/merchant-health?account=ACC-00047&metric=auth_rate&week=2026-09-21
A106: Platepost | B106: volume_drop | C106: low | D106: 46293 | E106: 46300 | F106: superseded | G106: payments_db | H106: Weekly processing volume fell 19% to $1.1M, from a $1.3M baseline. | I106: https://looker.internal.adyen.com/dashboards/merchant-health?account=ACC-00057&metric=volume&week=2026-09-21
A107: Sablewood Plus | B107: sev1_open | C107: high | D107: 46293 | G107: support | H107: Sev-1 support ticket open since 28 Sep. | I107: https://support.internal.adyen.com/tickets/SEV1-22597
A108: Dishdash Express | B108: no_contact_90d | C108: low | D108: 46294 | G108: gong | H108: No recorded call or QBR since 30 Jun 2026. | I108: https://app.gong.io/account?crm-id=00165LXcvhUtb3z
...

Sheet Weekly lists (output)
A1: Account Manager | B1: Rank | C1: Account Name | D1: Category | E1: Score | F1: Revenue at Risk (USD) | G1: Top Reason | H1: Hidden After Feedback | I1: Data Incomplete
A2: Sofia Marquez | B2: 1 | C2: Rentaroo | D2: Act Now | E2: 45.8 | F2: 0 | G2: Chargeback rate hit 1.85% (was 0.48%), above typical card-scheme monitoring thresholds (~0.9%). | H2: No | I2: No
A3: Sofia Marquez | B3: 2 | C3: Orbitra Trips | D3: Act Now | E3: 17.4 | F3: 0 | G3: Sev-1 support ticket open since 14 Sep. | H3: No | I3: No
A4: Sofia Marquez | B4: 3 | C4: Bazaarly | D4: Opportunity | E4: 9 | F4: 0 | G4: Weekly processing volume grew 26% to $2.0M, from a $1.6M baseline. | H4: No | I4: No
A5: Sofia Marquez | B5: 4 | C5: Snackrun | D5: Maintain | E5: 5.4 | F5: 0 | G5: Last QBR was on 24 Mar 2026, more than 180 days ago. | H5: No | I5: No
A6: Sofia Marquez | B6: 5 | C6: Mosswood Garden Centres | D6: Act Now | E6: 3.1 | F6: 0 | G6: Single-threaded: only Omar Castillo has engaged with us in the last 90 days. | H6: No | I6: No
A7: Sofia Marquez | B7: 6 | C7: Urban Kettle | D7: Maintain | E7: 2.9 | F7: 0 | G7: Last QBR was on 04 Mar 2026, more than 180 days ago. | H7: No | I7: No
A8: Sofia Marquez | B8: 7 | C8: Skyhaven Air | D8: Maintain | E8: 2.5 | F8: 0 | G8: No recorded call or QBR since 23 Jun 2026. | H8: No | I8: Yes
A9: Sofia Marquez | B9: 8 | C9: Zephyrine Plus | D9: Maintain | E9: 2.1 | F9: 0 | G9: No recorded call or QBR since 14 Jun 2026. | H9: No | I9: Yes
A10: Sofia Marquez | B10: 9 | C10: Larkspur Club | D10: Maintain | E10: 1.3 | F10: 0 | G10: No recorded call or QBR since 16 May 2026. | H10: No | I10: Yes
A11: Sofia Marquez | B11: 10 | C11: Emberly Exchange | D11: Maintain | E11: 1.1 | F11: 0 | G11: No recorded call or QBR since 26 May 2026. | H11: No | I11: Yes
A12: Sofia Marquez | B12: 11 | C12: Cobalt Crate | D12: Maintain | E12: 0.8 | F12: 0 | G12: No recorded call or QBR since 27 May 2026. | H12: No | I12: Yes
A13: Sofia Marquez | B13: 12 | C13: Pemberton Shoes | D13: Maintain | E13: 0.6 | F13: 0 | G13: Last QBR was on 13 Feb 2026, more than 180 days ago. | H13: No | I13: No
... A75: Jonas Berg | B75: 14 | C75: Cinderleaf Eats | D75: Maintain | E75: 0.4 | F75: 0 | G75: No recorded call or QBR since 09 May 2026. | H75: No | I75: Yes
